{
"meta":{"test_sets":[],"test_metrics":[],"learn_metrics":[{"best_value":"Min","name":"RMSE"}],"launch_mode":"Train","parameters":"","iteration_count":1000,"learn_sets":["learn"],"name":"experiment"},
"iterations":[
{"learn":[14.71798826],"iteration":0,"passed_time":0.1162712042,"remaining_time":116.154933},
{"learn":[14.34736728],"iteration":1,"passed_time":0.1178691743,"remaining_time":58.81671796},
{"learn":[13.96545696],"iteration":2,"passed_time":0.119967471,"remaining_time":39.86918954},
{"learn":[13.62248055],"iteration":3,"passed_time":0.122168126,"remaining_time":30.41986337},
{"learn":[13.26853122],"iteration":4,"passed_time":0.1242401761,"remaining_time":24.72379505},
{"learn":[12.95316436],"iteration":5,"passed_time":0.1268635115,"remaining_time":21.01705506},
{"learn":[12.6437975],"iteration":6,"passed_time":0.1291442938,"remaining_time":18.32004053},
{"learn":[12.38699532],"iteration":7,"passed_time":0.1312893147,"remaining_time":16.27987502},
{"learn":[12.13979118],"iteration":8,"passed_time":0.1337184168,"remaining_time":14.72388345},
{"learn":[11.84602831],"iteration":9,"passed_time":0.1360693602,"remaining_time":13.47086666},
{"learn":[11.56296345],"iteration":10,"passed_time":0.1385181771,"remaining_time":12.45404338},
{"learn":[11.31749247],"iteration":11,"passed_time":0.1409985235,"remaining_time":11.60887844},
{"learn":[11.11226525],"iteration":12,"passed_time":0.1434752382,"remaining_time":10.89308155},
{"learn":[10.86795345],"iteration":13,"passed_time":0.1459016482,"remaining_time":10.27564465},
{"learn":[10.63656449],"iteration":14,"passed_time":0.1480500089,"remaining_time":9.721950582},
{"learn":[10.39491603],"iteration":15,"passed_time":0.1502606797,"remaining_time":9.241031802},
{"learn":[10.16703119],"iteration":16,"passed_time":0.1526762253,"remaining_time":8.828278205},
{"learn":[9.953564928],"iteration":17,"passed_time":0.1554601537,"remaining_time":8.481215051},
{"learn":[9.75049189],"iteration":18,"passed_time":0.1581121992,"remaining_time":8.163582498},
{"learn":[9.560774962],"iteration":19,"passed_time":0.1610132677,"remaining_time":7.889650119},
{"learn":[9.406400138],"iteration":20,"passed_time":0.1634689248,"remaining_time":7.620765591},
{"learn":[9.240903536],"iteration":21,"passed_time":0.1661057221,"remaining_time":7.384154372},
{"learn":[9.062197912],"iteration":22,"passed_time":0.1682921333,"remaining_time":7.148757139},
{"learn":[8.893755489],"iteration":23,"passed_time":0.1706979723,"remaining_time":6.941717541},
{"learn":[8.726116231],"iteration":24,"passed_time":0.1732987871,"remaining_time":6.758652698},
{"learn":[8.591545513],"iteration":25,"passed_time":0.1759838381,"remaining_time":6.592625318},
{"learn":[8.444038352],"iteration":26,"passed_time":0.1783436263,"remaining_time":6.426975868},
{"learn":[8.310575166],"iteration":27,"passed_time":0.1812527827,"remaining_time":6.292060884},
{"learn":[8.184397076],"iteration":28,"passed_time":0.1840999742,"remaining_time":6.164175},
{"learn":[8.074151867],"iteration":29,"passed_time":0.1869306107,"remaining_time":6.044089745},
{"learn":[7.980370856],"iteration":30,"passed_time":0.1896121712,"remaining_time":5.926909479},
{"learn":[7.871652515],"iteration":31,"passed_time":0.1919415619,"remaining_time":5.806232248},
{"learn":[7.762569883],"iteration":32,"passed_time":0.1940605921,"remaining_time":5.686563411},
{"learn":[7.660883255],"iteration":33,"passed_time":0.1966965875,"remaining_time":5.588497164},
{"learn":[7.556356969],"iteration":34,"passed_time":0.1992393024,"remaining_time":5.493312194},
{"learn":[7.464121302],"iteration":35,"passed_time":0.201597862,"remaining_time":5.39834275},
{"learn":[7.372024804],"iteration":36,"passed_time":0.2039612187,"remaining_time":5.30850415},
{"learn":[7.296137458],"iteration":37,"passed_time":0.2063157925,"remaining_time":5.223047168},
{"learn":[7.209180869],"iteration":38,"passed_time":0.2090269931,"remaining_time":5.150639498},
{"learn":[7.124945419],"iteration":39,"passed_time":0.2112779119,"remaining_time":5.070669887},
{"learn":[7.063159904],"iteration":40,"passed_time":0.2125707351,"remaining_time":4.97208134},
{"learn":[6.996265616],"iteration":41,"passed_time":0.2146406106,"remaining_time":4.895850119},
{"learn":[6.919360911],"iteration":42,"passed_time":0.2160273266,"remaining_time":4.80786399},
{"learn":[6.860547199],"iteration":43,"passed_time":0.2185777787,"remaining_time":4.749099011},
{"learn":[6.794606056],"iteration":44,"passed_time":0.220635916,"remaining_time":4.68238444},
{"learn":[6.738708884],"iteration":45,"passed_time":0.2230303033,"remaining_time":4.625454551},
{"learn":[6.676766418],"iteration":46,"passed_time":0.2254251724,"remaining_time":4.570855092},
{"learn":[6.616787951],"iteration":47,"passed_time":0.2267787932,"remaining_time":4.497779399},
{"learn":[6.557032046],"iteration":48,"passed_time":0.229128807,"remaining_time":4.446969295},
{"learn":[6.498197864],"iteration":49,"passed_time":0.2312085954,"remaining_time":4.392963313},
{"learn":[6.447633529],"iteration":50,"passed_time":0.2335772151,"remaining_time":4.346368179},
{"learn":[6.399524211],"iteration":51,"passed_time":0.2356313688,"remaining_time":4.295741108},
{"learn":[6.35375345],"iteration":52,"passed_time":0.2377980566,"remaining_time":4.248957729},
{"learn":[6.299825955],"iteration":53,"passed_time":0.2397899182,"remaining_time":4.200764123},
{"learn":[6.256294307],"iteration":54,"passed_time":0.2417045323,"remaining_time":4.152923328},
{"learn":[6.217813211],"iteration":55,"passed_time":0.2438004877,"remaining_time":4.109779651},
{"learn":[6.181659456],"iteration":56,"passed_time":0.2450208513,"remaining_time":4.053590575},
{"learn":[6.145013399],"iteration":57,"passed_time":0.2469736807,"remaining_time":4.011193228},
{"learn":[6.113248721],"iteration":58,"passed_time":0.2490410408,"remaining_time":3.971993549},
{"learn":[6.077502356],"iteration":59,"passed_time":0.2509977736,"remaining_time":3.932298453},
{"learn":[6.047024781],"iteration":60,"passed_time":0.2530832177,"remaining_time":3.895821991},
{"learn":[6.016880598],"iteration":61,"passed_time":0.2551554353,"remaining_time":3.860254811},
{"learn":[5.978653695],"iteration":62,"passed_time":0.2572280458,"remaining_time":3.825756809},
{"learn":[5.939243413],"iteration":63,"passed_time":0.2592728822,"remaining_time":3.791865902},
{"learn":[5.911388944],"iteration":64,"passed_time":0.2612760108,"remaining_time":3.758354925},
{"learn":[5.880154577],"iteration":65,"passed_time":0.2633127158,"remaining_time":3.726273888},
{"learn":[5.850918399],"iteration":66,"passed_time":0.2646686239,"remaining_time":3.685609345},
{"learn":[5.819050593],"iteration":67,"passed_time":0.2662696936,"remaining_time":3.649461095},
{"learn":[5.802650291],"iteration":68,"passed_time":0.2681699323,"remaining_time":3.618350826},
{"learn":[5.770099152],"iteration":69,"passed_time":0.2701927039,"remaining_time":3.589703066},
{"learn":[5.745031186],"iteration":70,"passed_time":0.2721789021,"remaining_time":3.561326761},
{"learn":[5.725340982],"iteration":71,"passed_time":0.2742501569,"remaining_time":3.5347798},
{"learn":[5.70455304],"iteration":72,"passed_time":0.2763882503,"remaining_time":3.509752165},
{"learn":[5.681932352],"iteration":73,"passed_time":0.2784262361,"remaining_time":3.484090468},
{"learn":[5.6591158],"iteration":74,"passed_time":0.2806221678,"remaining_time":3.461006736},
{"learn":[5.638439546],"iteration":75,"passed_time":0.2827576608,"remaining_time":3.437737876},
{"learn":[5.619777202],"iteration":76,"passed_time":0.2849684205,"remaining_time":3.415920157},
{"learn":[5.597472057],"iteration":77,"passed_time":0.287013344,"remaining_time":3.392644913},
{"learn":[5.581494766],"iteration":78,"passed_time":0.2889264962,"remaining_time":3.368370924},
{"learn":[5.566470542],"iteration":79,"passed_time":0.2908762323,"remaining_time":3.345076672},
{"learn":[5.549106427],"iteration":80,"passed_time":0.293044945,"remaining_time":3.324793883},
{"learn":[5.532486935],"iteration":81,"passed_time":0.2944956027,"remaining_time":3.296914187},
{"learn":[5.518740342],"iteration":82,"passed_time":0.2965050785,"remaining_time":3.275845265},
{"learn":[5.500200697],"iteration":83,"passed_time":0.2986037158,"remaining_time":3.256202425},
{"learn":[5.480526587],"iteration":84,"passed_time":0.300498778,"remaining_time":3.234780964},
{"learn":[5.467112974],"iteration":85,"passed_time":0.3017562622,"remaining_time":3.207037484},
{"learn":[5.451040579],"iteration":86,"passed_time":0.3030052114,"remaining_time":3.179813311},
{"learn":[5.437746217],"iteration":87,"passed_time":0.3046820332,"remaining_time":3.157613799},
{"learn":[5.42518527],"iteration":88,"passed_time":0.3066721767,"remaining_time":3.139082617},
{"learn":[5.412975985],"iteration":89,"passed_time":0.310232841,"remaining_time":3.136798726},
{"learn":[5.398607268],"iteration":90,"passed_time":0.3121446133,"remaining_time":3.118015972},
{"learn":[5.385856497],"iteration":91,"passed_time":0.3139241329,"remaining_time":3.098294703},
{"learn":[5.374812712],"iteration":92,"passed_time":0.3160221007,"remaining_time":3.082065003},
{"learn":[5.367592597],"iteration":93,"passed_time":0.3174248342,"remaining_time":3.059435104},
{"learn":[5.356680409],"iteration":94,"passed_time":0.3186820573,"remaining_time":3.035865915},
{"learn":[5.342109361],"iteration":95,"passed_time":0.3208522089,"remaining_time":3.0213583},
{"learn":[5.33018821],"iteration":96,"passed_time":0.3224918853,"remaining_time":3.002166726},
{"learn":[5.318287308],"iteration":97,"passed_time":0.3245444914,"remaining_time":2.987133993},
{"learn":[5.306422803],"iteration":98,"passed_time":0.3265815016,"remaining_time":2.972221545},
{"learn":[5.297168324],"iteration":99,"passed_time":0.3278098301,"remaining_time":2.95028847},
{"learn":[5.28800712],"iteration":100,"passed_time":0.3297191946,"remaining_time":2.934827287},
{"learn":[5.280054475],"iteration":101,"passed_time":0.3314981613,"remaining_time":2.918483812},
{"learn":[5.269304887],"iteration":102,"passed_time":0.3334762475,"remaining_time":2.904157223},
{"learn":[5.257394242],"iteration":103,"passed_time":0.3351744156,"remaining_time":2.887656504},
{"learn":[5.249175242],"iteration":104,"passed_time":0.3370649355,"remaining_time":2.873077307},
{"learn":[5.242827606],"iteration":105,"passed_time":0.3389713301,"remaining_time":2.858871407},
{"learn":[5.233255774],"iteration":106,"passed_time":0.3409139515,"remaining_time":2.845197745},
{"learn":[5.227944788],"iteration":107,"passed_time":0.3425066459,"remaining_time":2.828851187},
{"learn":[5.221311105],"iteration":108,"passed_time":0.344244032,"remaining_time":2.813958097},
{"learn":[5.214638523],"iteration":109,"passed_time":0.3462129598,"remaining_time":2.801177584},
{"learn":[5.212905147],"iteration":110,"passed_time":0.3466504933,"remaining_time":2.776326923},
{"learn":[5.205948093],"iteration":111,"passed_time":0.3477802484,"remaining_time":2.757400541},
{"learn":[5.199260743],"iteration":112,"passed_time":0.3495423342,"remaining_time":2.743752658},
{"learn":[5.192919733],"iteration":113,"passed_time":0.350741259,"remaining_time":2.725936452},
{"learn":[5.187759039],"iteration":114,"passed_time":0.3526999749,"remaining_time":2.714256329},
{"learn":[5.184022032],"iteration":115,"passed_time":0.3545626228,"remaining_time":2.702011711},
{"learn":[5.176834662],"iteration":116,"passed_time":0.3562034338,"remaining_time":2.688270359},
{"learn":[5.172180634],"iteration":117,"passed_time":0.3575985942,"remaining_time":2.672897967},
{"learn":[5.167940035],"iteration":118,"passed_time":0.3585235258,"remaining_time":2.654279212},
{"learn":[5.159710017],"iteration":119,"passed_time":0.3600660691,"remaining_time":2.640484507},
{"learn":[5.154170714],"iteration":120,"passed_time":0.3617754978,"remaining_time":2.628104649},
{"learn":[5.150249623],"iteration":121,"passed_time":0.3636699862,"remaining_time":2.61723154},
{"learn":[5.145351531],"iteration":122,"passed_time":0.3656811022,"remaining_time":2.607335989},
{"learn":[5.137247404],"iteration":123,"passed_time":0.3673279276,"remaining_time":2.594994069},
{"learn":[5.133404727],"iteration":124,"passed_time":0.3690797663,"remaining_time":2.583558364},
{"learn":[5.126553864],"iteration":125,"passed_time":0.3709070577,"remaining_time":2.57279975},
{"learn":[5.119849897],"iteration":126,"passed_time":0.3725958512,"remaining_time":2.561229749},
{"learn":[5.116117349],"iteration":127,"passed_time":0.3742681763,"remaining_time":2.549701951},
{"learn":[5.109015492],"iteration":128,"passed_time":0.376015062,"remaining_time":2.53883038},
{"learn":[5.105066715],"iteration":129,"passed_time":0.3775731629,"remaining_time":2.526835783},
{"learn":[5.096977309],"iteration":130,"passed_time":0.3791906159,"remaining_time":2.515394238},
{"learn":[5.091565906],"iteration":131,"passed_time":0.3806104956,"remaining_time":2.50280235},
{"learn":[5.086455717],"iteration":132,"passed_time":0.3822745167,"remaining_time":2.49196997},
{"learn":[5.081523939],"iteration":133,"passed_time":0.3837907889,"remaining_time":2.480319576},
{"learn":[5.077731225],"iteration":134,"passed_time":0.3853318631,"remaining_time":2.468978234},
{"learn":[5.069490834],"iteration":135,"passed_time":0.3867840945,"remaining_time":2.4572166},
{"learn":[5.066341098],"iteration":136,"passed_time":0.3882213717,"remaining_time":2.445511268},
{"learn":[5.062046422],"iteration":137,"passed_time":0.3898410601,"remaining_time":2.435094158},
{"learn":[5.053697218],"iteration":138,"passed_time":0.3914930365,"remaining_time":2.425003629},
{"learn":[5.04968545],"iteration":139,"passed_time":0.3930181935,"remaining_time":2.414254617},
{"learn":[5.047222516],"iteration":140,"passed_time":0.3941089615,"remaining_time":2.400990056},
{"learn":[5.042186938],"iteration":141,"passed_time":0.3957559771,"remaining_time":2.391257946},
{"learn":[5.033577034],"iteration":142,"passed_time":0.3972916463,"remaining_time":2.380971615},
{"learn":[5.02609879],"iteration":143,"passed_time":0.3987789991,"remaining_time":2.370519606},
{"learn":[5.021296624],"iteration":144,"passed_time":0.4002050264,"remaining_time":2.359829638},
{"learn":[5.01529187],"iteration":145,"passed_time":0.4017194973,"remaining_time":2.349783909},
{"learn":[5.012031908],"iteration":146,"passed_time":0.4031663936,"remaining_time":2.339462134},
{"learn":[5.006787924],"iteration":147,"passed_time":0.4046339293,"remaining_time":2.329379106},
{"learn":[5.001717454],"iteration":148,"passed_time":0.4059385772,"remaining_time":2.318481404},
{"learn":[4.995839168],"iteration":149,"passed_time":0.4075180039,"remaining_time":2.309268689},
{"learn":[4.992541484],"iteration":150,"passed_time":0.4091323157,"remaining_time":2.300353219},
{"learn":[4.987193392],"iteration":151,"passed_time":0.4107550034,"remaining_time":2.291580545},
{"learn":[4.981479737],"iteration":152,"passed_time":0.4122670732,"remaining_time":2.282288961},
{"learn":[4.978627675],"iteration":153,"passed_time":0.413743568,"remaining_time":2.272902978},
{"learn":[4.975369408],"iteration":154,"passed_time":0.4154271264,"remaining_time":2.264747883},
{"learn":[4.971193179],"iteration":155,"passed_time":0.4169108091,"remaining_time":2.255594378},
{"learn":[4.967938665],"iteration":156,"passed_time":0.4184437163,"remaining_time":2.246802884},
{"learn":[4.964174183],"iteration":157,"passed_time":0.4199109816,"remaining_time":2.237753459},
{"learn":[4.957977502],"iteration":158,"passed_time":0.4213868997,"remaining_time":2.228845174},
{"learn":[4.954008391],"iteration":159,"passed_time":0.4228653654,"remaining_time":2.220043168},
{"learn":[4.948879982],"iteration":160,"passed_time":0.4243041886,"remaining_time":2.211125554},
{"learn":[4.944714072],"iteration":161,"passed_time":0.4255715045,"remaining_time":2.201413091},
{"learn":[4.943473043],"iteration":162,"passed_time":0.4263909569,"remaining_time":2.189504484},
{"learn":[4.941007966],"iteration":163,"passed_time":0.4280164785,"remaining_time":2.181840097},
{"learn":[4.936378826],"iteration":164,"passed_time":0.4294247264,"remaining_time":2.173149373},
{"learn":[4.932158835],"iteration":165,"passed_time":0.4306600625,"remaining_time":2.163677663},
{"learn":[4.92990716],"iteration":166,"passed_time":0.4319514581,"remaining_time":2.154584219},
{"learn":[4.929277739],"iteration":167,"passed_time":0.4325732433,"remaining_time":2.14226749},
{"learn":[4.925556143],"iteration":168,"passed_time":0.4339129473,"remaining_time":2.133619285},
{"learn":[4.922629797],"iteration":169,"passed_time":0.4351303531,"remaining_time":2.124459959},
{"learn":[4.918379257],"iteration":170,"passed_time":0.4364094942,"remaining_time":2.115692811},
{"learn":[4.91351799],"iteration":171,"passed_time":0.437944708,"remaining_time":2.108245455},
{"learn":[4.908722526],"iteration":172,"passed_time":0.4394027463,"remaining_time":2.100497521},
{"learn":[4.902519148],"iteration":173,"passed_time":0.440776826,"remaining_time":2.092423323},
{"learn":[4.899112454],"iteration":174,"passed_time":0.4420778194,"remaining_time":2.084081148},
{"learn":[4.895814141],"iteration":175,"passed_time":0.443309609,"remaining_time":2.075494987},
{"learn":[4.889771674],"iteration":176,"passed_time":0.4446744771,"remaining_time":2.067610704},
{"learn":[4.887147662],"iteration":177,"passed_time":0.4460919447,"remaining_time":2.060042576},
{"learn":[4.881385127],"iteration":178,"passed_time":0.4474103935,"remaining_time":2.052089011},
{"learn":[4.876378169],"iteration":179,"passed_time":0.4485063756,"remaining_time":2.043195711},
{"learn":[4.87271711],"iteration":180,"passed_time":0.4497166476,"remaining_time":2.034905715},
{"learn":[4.86925264],"iteration":181,"passed_time":0.4507964992,"remaining_time":2.026107342},
{"learn":[4.866108612],"iteration":182,"passed_time":0.4520419892,"remaining_time":2.018132815},
{"learn":[4.862087991],"iteration":183,"passed_time":0.4533816366,"remaining_time":2.010648997},
{"learn":[4.858844101],"iteration":184,"passed_time":0.4545695545,"remaining_time":2.002563172},
{"learn":[4.856146904],"iteration":185,"passed_time":0.455691816,"remaining_time":1.994264184},
{"learn":[4.853703934],"iteration":186,"passed_time":0.4570153528,"remaining_time":1.986917015},
{"learn":[4.849438069],"iteration":187,"passed_time":0.4582715401,"remaining_time":1.979343035},
{"learn":[4.84729187],"iteration":188,"passed_time":0.459461687,"remaining_time":1.97155253},
{"learn":[4.842756167],"iteration":189,"passed_time":0.4606773514,"remaining_time":1.963940288},
{"learn":[4.836842837],"iteration":190,"passed_time":0.4618234329,"remaining_time":1.9561003},
{"learn":[4.834006859],"iteration":191,"passed_time":0.4627822132,"remaining_time":1.947541814},
{"learn":[4.830860107],"iteration":192,"passed_time":0.4638825381,"remaining_time":1.939653929},
{"learn":[4.828678805],"iteration":193,"passed_time":0.4651001953,"remaining_time":1.932323492},
{"learn":[4.826530539],"iteration":194,"passed_time":0.4662482615,"remaining_time":1.924768464},
{"learn":[4.824802515],"iteration":195,"passed_time":0.4673604222,"remaining_time":1.917131528},
{"learn":[4.821553331],"iteration":196,"passed_time":0.4684344632,"remaining_time":1.909405451},
{"learn":[4.819816584],"iteration":197,"passed_time":0.4694952447,"remaining_time":1.90169286},
{"learn":[4.81688446],"iteration":198,"passed_time":0.4706064761,"remaining_time":1.894250188},
{"learn":[4.813848218],"iteration":199,"passed_time":0.471658407,"remaining_time":1.886633628},
{"learn":[4.810006161],"iteration":200,"passed_time":0.4728544275,"remaining_time":1.879655162},
{"learn":[4.805559592],"iteration":201,"passed_time":0.4740236665,"remaining_time":1.872628148},
{"learn":[4.802506442],"iteration":202,"passed_time":0.475141556,"remaining_time":1.865457242},
{"learn":[4.797892186],"iteration":203,"passed_time":0.4762307726,"remaining_time":1.858233799},
{"learn":[4.793347995],"iteration":204,"passed_time":0.4773287931,"remaining_time":1.851104344},
{"learn":[4.787805359],"iteration":205,"passed_time":0.478515776,"remaining_time":1.84437634},
{"learn":[4.784985136],"iteration":206,"passed_time":0.4796097065,"remaining_time":1.837345397},
{"learn":[4.781627828],"iteration":207,"passed_time":0.4807292507,"remaining_time":1.83046907},
{"learn":[4.779647691],"iteration":208,"passed_time":0.4817447536,"remaining_time":1.823254068},
{"learn":[4.77801683],"iteration":209,"passed_time":0.4828435763,"remaining_time":1.816411549},
{"learn":[4.774320551],"iteration":210,"passed_time":0.4839879116,"remaining_time":1.80979366},
{"learn":[4.770022679],"iteration":211,"passed_time":0.485160044,"remaining_time":1.80333073},
{"learn":[4.767800367],"iteration":212,"passed_time":0.4863202946,"remaining_time":1.796873577},
{"learn":[4.76251358],"iteration":213,"passed_time":0.4874025882,"remaining_time":1.7901796},
{"learn":[4.759939303],"iteration":214,"passed_time":0.4884890936,"remaining_time":1.783553202},
{"learn":[4.755263949],"iteration":215,"passed_time":0.4895165687,"remaining_time":1.776763842},
{"learn":[4.753305796],"iteration":216,"passed_time":0.4905517552,"remaining_time":1.770055412},
{"learn":[4.748349763],"iteration":217,"passed_time":0.4915309963,"remaining_time":1.763198344},
{"learn":[4.746971894],"iteration":218,"passed_time":0.4925670981,"remaining_time":1.756597734},
{"learn":[4.743035018],"iteration":219,"passed_time":0.4935636927,"remaining_time":1.749907638},
{"learn":[4.741035788],"iteration":220,"passed_time":0.4945038864,"remaining_time":1.74307026},
{"learn":[4.738548183],"iteration":221,"passed_time":0.4954639462,"remaining_time":1.736355631},
{"learn":[4.735185176],"iteration":222,"passed_time":0.496556368,"remaining_time":1.730153802},
{"learn":[4.732875791],"iteration":223,"passed_time":0.497618362,"remaining_time":1.723892183},
{"learn":[4.729817282],"iteration":224,"passed_time":0.4986917802,"remaining_time":1.717716132},
{"learn":[4.72437331],"iteration":225,"passed_time":0.499698734,"remaining_time":1.711357611},
{"learn":[4.722253332],"iteration":226,"passed_time":0.5007724757,"remaining_time":1.705273673},
{"learn":[4.720297413],"iteration":227,"passed_time":0.5018724404,"remaining_time":1.699322474},
{"learn":[4.715958981],"iteration":228,"passed_time":0.5029215789,"remaining_time":1.693242521},
{"learn":[4.712405794],"iteration":229,"passed_time":0.5040221324,"remaining_time":1.687378443},
{"learn":[4.71076205],"iteration":230,"passed_time":0.5049727164,"remaining_time":1.681056359},
{"learn":[4.705892246],"iteration":231,"passed_time":0.5059511975,"remaining_time":1.67487293},
{"learn":[4.704219812],"iteration":232,"passed_time":0.5069521834,"remaining_time":1.66880826},
{"learn":[4.701780615],"iteration":233,"passed_time":0.5078746262,"remaining_time":1.662529759},
{"learn":[4.69855483],"iteration":234,"passed_time":0.5089742234,"remaining_time":1.656873536},
{"learn":[4.694004564],"iteration":235,"passed_time":0.5101074864,"remaining_time":1.651364914},
{"learn":[4.690929095],"iteration":236,"passed_time":0.5110676199,"remaining_time":1.645335839},
{"learn":[4.688941126],"iteration":237,"passed_time":0.5120536355,"remaining_time":1.639432228},
{"learn":[4.686464188],"iteration":238,"passed_time":0.5130523162,"remaining_time":1.633610095},
{"learn":[4.684242807],"iteration":239,"passed_time":0.5141068526,"remaining_time":1.628005033},
{"learn":[4.68193744],"iteration":240,"passed_time":0.5150461631,"remaining_time":1.622074846},
{"learn":[4.678991506],"iteration":241,"passed_time":0.5160828762,"remaining_time":1.616490992},
{"learn":[4.675563038],"iteration":242,"passed_time":0.5171539434,"remaining_time":1.611051585},
{"learn":[4.669965825],"iteration":243,"passed_time":0.5181238181,"remaining_time":1.605334453},
{"learn":[4.66564654],"iteration":244,"passed_time":0.5191157371,"remaining_time":1.599724006},
{"learn":[4.663509348],"iteration":245,"passed_time":0.5201041636,"remaining_time":1.594140404},
{"learn":[4.661247953],"iteration":246,"passed_time":0.5212454932,"remaining_time":1.589060147},
{"learn":[4.657118686],"iteration":247,"passed_time":0.5223404737,"remaining_time":1.583871114},
{"learn":[4.655842983],"iteration":248,"passed_time":0.523301641,"remaining_time":1.578311375},
{"learn":[4.65222607],"iteration":249,"passed_time":0.5242350766,"remaining_time":1.57270523},
{"learn":[4.651157253],"iteration":250,"passed_time":0.5251554887,"remaining_time":1.567097454},
{"learn":[4.647659655],"iteration":251,"passed_time":0.5260452474,"remaining_time":1.561435893},
{"learn":[4.645312325],"iteration":252,"passed_time":0.5270728384,"remaining_time":1.556219013},
{"learn":[4.644994648],"iteration":253,"passed_time":0.5280627067,"remaining_time":1.550924327},
{"learn":[4.642908866],"iteration":254,"passed_time":0.5289696884,"remaining_time":1.545421246},
{"learn":[4.641543743],"iteration":255,"passed_time":0.5298654385,"remaining_time":1.539921431},
{"learn":[4.639394956],"iteration":256,"passed_time":0.5308671586,"remaining_time":1.534763809},
{"learn":[4.634721211],"iteration":257,"passed_time":0.5318255018,"remaining_time":1.529513652},
{"learn":[4.632554786],"iteration":258,"passed_time":0.5328141479,"remaining_time":1.524383334},
{"learn":[4.631264022],"iteration":259,"passed_time":0.5337238733,"remaining_time":1.519060255},
{"learn":[4.629239554],"iteration":260,"passed_time":0.5346368625,"remaining_time":1.513780235},
{"learn":[4.626179768],"iteration":261,"passed_time":0.5356635765,"remaining_time":1.508853891},
{"learn":[4.617912472],"iteration":262,"passed_time":0.5365770473,"remaining_time":1.503639863},
{"learn":[4.616115938],"iteration":263,"passed_time":0.537498979,"remaining_time":1.498482002},
{"learn":[4.613956845],"iteration":264,"passed_time":0.5384844713,"remaining_time":1.493532401},
{"learn":[4.61011909],"iteration":265,"passed_time":0.5395749303,"remaining_time":1.488902251},
{"learn":[4.606094727],"iteration":266,"passed_time":0.5405337553,"remaining_time":1.483937238},
{"learn":[4.604223841],"iteration":267,"passed_time":0.5417058143,"remaining_time":1.479584538},
{"learn":[4.600828534],"iteration":268,"passed_time":0.5426467957,"remaining_time":1.474627538},
{"learn":[4.597364193],"iteration":269,"passed_time":0.5436003087,"remaining_time":1.469734168},
{"learn":[4.593649744],"iteration":270,"passed_time":0.5444819773,"remaining_time":1.464676611},
{"learn":[4.588029321],"iteration":271,"passed_time":0.5454295324,"remaining_time":1.459826102},
{"learn":[4.58556893],"iteration":272,"passed_time":0.5464834647,"remaining_time":1.455287468},
{"learn":[4.583261225],"iteration":273,"passed_time":0.5474742835,"remaining_time":1.450607043},
{"learn":[4.578158628],"iteration":274,"passed_time":0.5484232178,"remaining_time":1.445843029},
{"learn":[4.573338432],"iteration":275,"passed_time":0.5494153186,"remaining_time":1.441219894},
{"learn":[4.566872836],"iteration":276,"passed_time":0.5503854046,"remaining_time":1.436565514},
{"learn":[4.563351023],"iteration":277,"passed_time":0.5513154833,"remaining_time":1.431833737},
{"learn":[4.557414166],"iteration":278,"passed_time":0.5522563675,"remaining_time":1.427157136},
{"learn":[4.555228369],"iteration":279,"passed_time":0.5531228363,"remaining_time":1.422315865},
{"learn":[4.550057286],"iteration":280,"passed_time":0.554168292,"remaining_time":1.417960861},
{"learn":[4.547894945],"iteration":281,"passed_time":0.5551482084,"remaining_time":1.41346246},
{"learn":[4.540236025],"iteration":282,"passed_time":0.556187202,"remaining_time":1.4091386},
{"learn":[4.536008956],"iteration":283,"passed_time":0.5573511113,"remaining_time":1.405152802},
{"learn":[4.530807601],"iteration":284,"passed_time":0.5583428342,"remaining_time":1.40075483},
{"learn":[4.526448118],"iteration":285,"passed_time":0.559390609,"remaining_time":1.396520611},
{"learn":[4.523469416],"iteration":286,"passed_time":0.5604494119,"remaining_time":1.392335995},
{"learn":[4.520897614],"iteration":287,"passed_time":0.5613670501,"remaining_time":1.387824096},
{"learn":[4.516054787],"iteration":288,"passed_time":0.5623093618,"remaining_time":1.383397772},
{"learn":[4.512514254],"iteration":289,"passed_time":0.5633263573,"remaining_time":1.379178323},
{"learn":[4.506516517],"iteration":290,"passed_time":0.5643732314,"remaining_time":1.375053681},
{"learn":[4.504119405],"iteration":291,"passed_time":0.565293349,"remaining_time":1.370642778},
{"learn":[4.498939912],"iteration":292,"passed_time":0.5661998701,"remaining_time":1.366222895},
{"learn":[4.493636525],"iteration":293,"passed_time":0.5671992057,"remaining_time":1.362049793},
{"learn":[4.491042136],"iteration":294,"passed_time":0.5681859662,"remaining_time":1.357868157},
{"learn":[4.486512928],"iteration":295,"passed_time":0.5691529277,"remaining_time":1.353661017},
{"learn":[4.485416522],"iteration":296,"passed_time":0.5701597786,"remaining_time":1.349570116},
{"learn":[4.480614096],"iteration":297,"passed_time":0.5711127731,"remaining_time":1.345373043},
{"learn":[4.478652367],"iteration":298,"passed_time":0.5719994713,"remaining_time":1.341042239},
{"learn":[4.473879954],"iteration":299,"passed_time":0.5728863161,"remaining_time":1.336734737},
{"learn":[4.468975722],"iteration":300,"passed_time":0.573876662,"remaining_time":1.332690321},
{"learn":[4.465287479],"iteration":301,"passed_time":0.5747819155,"remaining_time":1.32846946},
{"learn":[4.457619053],"iteration":302,"passed_time":0.5756918479,"remaining_time":1.324281247},
{"learn":[4.455640701],"iteration":303,"passed_time":0.576604834,"remaining_time":1.320121594},
{"learn":[4.450509867],"iteration":304,"passed_time":0.5775131643,"remaining_time":1.31597262},
{"learn":[4.448973986],"iteration":305,"passed_time":0.5784856225,"remaining_time":1.311990268},
{"learn":[4.443707619],"iteration":306,"passed_time":0.579512433,"remaining_time":1.308150215},
{"learn":[4.438198327],"iteration":307,"passed_time":0.5805003603,"remaining_time":1.304241069},
{"learn":[4.434733052],"iteration":308,"passed_time":0.5813987965,"remaining_time":1.300150707},
{"learn":[4.43051256],"iteration":309,"passed_time":0.582333763,"remaining_time":1.296162247},
{"learn":[4.429064434],"iteration":310,"passed_time":0.583300746,"remaining_time":1.292264354},
{"learn":[4.423966496],"iteration":311,"passed_time":0.5843426314,"remaining_time":1.288550418},
{"learn":[4.423344505],"iteration":312,"passed_time":0.5852108854,"remaining_time":1.284472454},
{"learn":[4.416195237],"iteration":313,"passed_time":0.5861244514,"remaining_time":1.280513929},
{"learn":[4.408374013],"iteration":314,"passed_time":0.5870174289,"remaining_time":1.276529964},
{"learn":[4.403636914],"iteration":315,"passed_time":0.5880319308,"remaining_time":1.27282861},
{"learn":[4.398475605],"iteration":316,"passed_time":0.5889529567,"remaining_time":1.268942806},
{"learn":[4.39323912],"iteration":317,"passed_time":0.5899480423,"remaining_time":1.265234481},
{"learn":[4.389184219],"iteration":318,"passed_time":0.5908392652,"remaining_time":1.261321441},
{"learn":[4.384997038],"iteration":319,"passed_time":0.5918079326,"remaining_time":1.257591857},
{"learn":[4.380579421],"iteration":320,"passed_time":0.5927570369,"remaining_time":1.253838094},
{"learn":[4.377902285],"iteration":321,"passed_time":0.5935949085,"remaining_time":1.24986754},
{"learn":[4.376045373],"iteration":322,"passed_time":0.5945125965,"remaining_time":1.246083678},
{"learn":[4.375358429],"iteration":323,"passed_time":0.5954512742,"remaining_time":1.242361301},
{"learn":[4.37124832],"iteration":324,"passed_time":0.5964501673,"remaining_time":1.238781117},
{"learn":[4.370409548],"iteration":325,"passed_time":0.5974029645,"remaining_time":1.235121466},
{"learn":[4.366571252],"iteration":326,"passed_time":0.5983859516,"remaining_time":1.231540506},
{"learn":[4.364812224],"iteration":327,"passed_time":0.5993846413,"remaining_time":1.228007558},
{"learn":[4.364301192],"iteration":328,"passed_time":0.6002501625,"remaining_time":1.224218417},
{"learn":[4.360187111],"iteration":329,"passed_time":0.6011246906,"remaining_time":1.220465281},
{"learn":[4.357746347],"iteration":330,"passed_time":0.6021767305,"remaining_time":1.217088316},
{"learn":[4.353894231],"iteration":331,"passed_time":0.6031627893,"remaining_time":1.2135926},
{"learn":[4.349994831],"iteration":332,"passed_time":0.6041091293,"remaining_time":1.2100324},
{"learn":[4.346860703],"iteration":333,"passed_time":0.6049632487,"remaining_time":1.206303963},
{"learn":[4.34333304],"iteration":334,"passed_time":0.6059765568,"remaining_time":1.202908687},
{"learn":[4.339282404],"iteration":335,"passed_time":0.6069147404,"remaining_time":1.19937913},
{"learn":[4.338296289],"iteration":336,"passed_time":0.6078939339,"remaining_time":1.195945632},
{"learn":[4.336740164],"iteration":337,"passed_time":0.6088464993,"remaining_time":1.192474505},
{"learn":[4.333543979],"iteration":338,"passed_time":0.6098366318,"remaining_time":1.189091486},
{"learn":[4.328781065],"iteration":339,"passed_time":0.6107488289,"remaining_time":1.185571256},
{"learn":[4.325732534],"iteration":340,"passed_time":0.6117396741,"remaining_time":1.182218314},
{"learn":[4.324437945],"iteration":341,"passed_time":0.6125933727,"remaining_time":1.178615319},
{"learn":[4.322813289],"iteration":342,"passed_time":0.6135727156,"remaining_time":1.175269021},
{"learn":[4.31875056],"iteration":343,"passed_time":0.614542563,"remaining_time":1.171918376},
{"learn":[4.317656719],"iteration":344,"passed_time":0.6154490918,"remaining_time":1.168461319},
{"learn":[4.312930112],"iteration":345,"passed_time":0.6163725653,"remaining_time":1.165051034},
{"learn":[4.30846482],"iteration":346,"passed_time":0.6173863536,"remaining_time":1.16182504},
{"learn":[4.30479707],"iteration":347,"passed_time":0.6183128411,"remaining_time":1.158448197},
{"learn":[4.301073656],"iteration":348,"passed_time":0.6192197926,"remaining_time":1.155048954},
{"learn":[4.297766059],"iteration":349,"passed_time":0.6201869553,"remaining_time":1.151775774},
{"learn":[4.293335229],"iteration":350,"passed_time":0.6212434027,"remaining_time":1.148680822},
{"learn":[4.289873158],"iteration":351,"passed_time":0.6222092244,"remaining_time":1.145430618},
{"learn":[4.28660093],"iteration":352,"passed_time":0.6232654101,"remaining_time":1.142358981},
{"learn":[4.283111199],"iteration":353,"passed_time":0.6242594969,"remaining_time":1.13918541},
{"learn":[4.278814558],"iteration":354,"passed_time":0.625204084,"remaining_time":1.135934181},
{"learn":[4.275269236],"iteration":355,"passed_time":0.6261409286,"remaining_time":1.132681905},
{"learn":[4.272772344],"iteration":356,"passed_time":0.6270097439,"remaining_time":1.129320071},
{"learn":[4.26985559],"iteration":357,"passed_time":0.6280022896,"remaining_time":1.12619405},
{"learn":[4.264160189],"iteration":358,"passed_time":0.6288714928,"remaining_time":1.122859685},
{"learn":[4.261402594],"iteration":359,"passed_time":0.6297353683,"remaining_time":1.119529544},
{"learn":[4.256141476],"iteration":360,"passed_time":0.6308316288,"remaining_time":1.116624407},
{"learn":[4.253946602],"iteration":361,"passed_time":0.6318247654,"remaining_time":1.113547515},
{"learn":[4.248756369],"iteration":362,"passed_time":0.6327832441,"remaining_time":1.110421285},
{"learn":[4.244050951],"iteration":363,"passed_time":0.6337732713,"remaining_time":1.107362089},
{"learn":[4.239788234],"iteration":364,"passed_time":0.6346558348,"remaining_time":1.104127274},
{"learn":[4.235155302],"iteration":365,"passed_time":0.6356573572,"remaining_time":1.101111378},
{"learn":[4.228840796],"iteration":366,"passed_time":0.6365885616,"remaining_time":1.097985176},
{"learn":[4.226542371],"iteration":367,"passed_time":0.6375147803,"remaining_time":1.09486234},
{"learn":[4.225608561],"iteration":368,"passed_time":0.6384631888,"remaining_time":1.091789355},
{"learn":[4.222496277],"iteration":369,"passed_time":0.6394498263,"remaining_time":1.088792947},
{"learn":[4.220197087],"iteration":370,"passed_time":0.6403337255,"remaining_time":1.08563319},
{"learn":[4.219288916],"iteration":371,"passed_time":0.6412064958,"remaining_time":1.08246688},
{"learn":[4.218100315],"iteration":372,"passed_time":0.6420395727,"remaining_time":1.079246145},
{"learn":[4.214754138],"iteration":373,"passed_time":0.6429258058,"remaining_time":1.076127151},
{"learn":[4.212275752],"iteration":374,"passed_time":0.6438445873,"remaining_time":1.073074312},
{"learn":[4.211517093],"iteration":375,"passed_time":0.644800152,"remaining_time":1.070093869},
{"learn":[4.209015938],"iteration":376,"passed_time":0.6457657609,"remaining_time":1.067140767},
{"learn":[4.205067162],"iteration":377,"passed_time":0.6466989113,"remaining_time":1.064144769},
{"learn":[4.202796277],"iteration":378,"passed_time":0.6476388289,"remaining_time":1.061170746},
{"learn":[4.198083496],"iteration":379,"passed_time":0.6485730753,"remaining_time":1.058198176},
{"learn":[4.194243663],"iteration":380,"passed_time":0.6496282604,"remaining_time":1.05543279},
{"learn":[4.192692763],"iteration":381,"passed_time":0.6506589138,"remaining_time":1.052636672},
{"learn":[4.189488917],"iteration":382,"passed_time":0.6517072676,"remaining_time":1.049878288},
{"learn":[4.186791117],"iteration":383,"passed_time":0.652893804,"remaining_time":1.047350477},
{"learn":[4.18190118],"iteration":384,"passed_time":0.6539454191,"remaining_time":1.044614111},
{"learn":[4.177585633],"iteration":385,"passed_time":0.6550598278,"remaining_time":1.041986358},
{"learn":[4.174152811],"iteration":386,"passed_time":0.6562010721,"remaining_time":1.039408933},
{"learn":[4.168108876],"iteration":387,"passed_time":0.6570735388,"remaining_time":1.036414963},
{"learn":[4.164929402],"iteration":388,"passed_time":0.658125799,"remaining_time":1.033714301},
{"learn":[4.161047196],"iteration":389,"passed_time":0.659070135,"remaining_time":1.030853288},
{"learn":[4.159165651],"iteration":390,"passed_time":0.6599540664,"remaining_time":1.027907996},
{"learn":[4.153882299],"iteration":391,"passed_time":0.6608658685,"remaining_time":1.025016449},
{"learn":[4.153215545],"iteration":392,"passed_time":0.6618716166,"remaining_time":1.02228008},
{"learn":[4.149519448],"iteration":393,"passed_time":0.6628669481,"remaining_time":1.019536473},
{"learn":[4.144762133],"iteration":394,"passed_time":0.66377989,"remaining_time":1.016675528},
{"learn":[4.141596818],"iteration":395,"passed_time":0.6646828406,"remaining_time":1.013809181},
{"learn":[4.138991592],"iteration":396,"passed_time":0.6656817574,"remaining_time":1.011098488},
{"learn":[4.138730315],"iteration":397,"passed_time":0.6665376858,"remaining_time":1.008180118},
{"learn":[4.136623461],"iteration":398,"passed_time":0.667547345,"remaining_time":1.005503645},
{"learn":[4.132898506],"iteration":399,"passed_time":0.668522056,"remaining_time":1.002783084},
{"learn":[4.132334523],"iteration":400,"passed_time":0.6695024346,"remaining_time":1.000079697},
{"learn":[4.127705917],"iteration":401,"passed_time":0.6705880581,"remaining_time":0.9975414396},
{"learn":[4.12480131],"iteration":402,"passed_time":0.6716173039,"remaining_time":0.9949268745},
{"learn":[4.121170651],"iteration":403,"passed_time":0.6725424158,"remaining_time":0.9921665341},
{"learn":[4.119407059],"iteration":404,"passed_time":0.6734258408,"remaining_time":0.9893540131},
{"learn":[4.117360351],"iteration":405,"passed_time":0.674351776,"remaining_time":0.9866131896},
{"learn":[4.114770247],"iteration":406,"passed_time":0.6753508944,"remaining_time":0.9839879125},
{"learn":[4.113856248],"iteration":407,"passed_time":0.6762508811,"remaining_time":0.9812267686},
{"learn":[4.109477302],"iteration":408,"passed_time":0.6772320592,"remaining_time":0.9785920465},
{"learn":[4.105658683],"iteration":409,"passed_time":0.6781770841,"remaining_time":0.9759133649},
{"learn":[4.104884478],"iteration":410,"passed_time":0.6790748414,"remaining_time":0.973175381},
{"learn":[4.099292681],"iteration":411,"passed_time":0.6800764125,"remaining_time":0.9705944916},
{"learn":[4.098176116],"iteration":412,"passed_time":0.6811128533,"remaining_time":0.9680708108},
{"learn":[4.093939029],"iteration":413,"passed_time":0.6820143299,"remaining_time":0.9653632786},
{"learn":[4.093601091],"iteration":414,"passed_time":0.6829023331,"remaining_time":0.9626454575},
{"learn":[4.091429142],"iteration":415,"passed_time":0.68386798,"remaining_time":0.9600454334},
{"learn":[4.091055731],"iteration":416,"passed_time":0.6847814173,"remaining_time":0.9573802549},
{"learn":[4.087439537],"iteration":417,"passed_time":0.6857572404,"remaining_time":0.9548103204},
{"learn":[4.081884541],"iteration":418,"passed_time":0.6868324379,"remaining_time":0.9523857909},
{"learn":[4.081421652],"iteration":419,"passed_time":0.687729994,"remaining_time":0.9497223727},
{"learn":[4.078220955],"iteration":420,"passed_time":0.6886121471,"remaining_time":0.9470461595},
{"learn":[4.074758657],"iteration":421,"passed_time":0.6895147648,"remaining_time":0.9444064788},
{"learn":[4.07277594],"iteration":422,"passed_time":0.6905042146,"remaining_time":0.9418934558},
{"learn":[4.072551284],"iteration":423,"passed_time":0.6912262541,"remaining_time":0.9390243452},
{"learn":[4.071943133],"iteration":424,"passed_time":0.6921003316,"remaining_time":0.9363710368},
{"learn":[4.068520465],"iteration":425,"passed_time":0.692976395,"remaining_time":0.9337287575},
{"learn":[4.064751921],"iteration":426,"passed_time":0.6939233707,"remaining_time":0.9311899096},
{"learn":[4.059365195],"iteration":427,"passed_time":0.694935341,"remaining_time":0.9287453623},
{"learn":[4.055913491],"iteration":428,"passed_time":0.6959519473,"remaining_time":0.9263136642},
{"learn":[4.051902815],"iteration":429,"passed_time":0.6968894743,"remaining_time":0.9237837218},
{"learn":[4.048801808],"iteration":430,"passed_time":0.6978164859,"remaining_time":0.9212472865},
{"learn":[4.044692792],"iteration":431,"passed_time":0.6987239672,"remaining_time":0.9186926235},
{"learn":[4.043839458],"iteration":432,"passed_time":0.6996940657,"remaining_time":0.916227564},
{"learn":[4.042705605],"iteration":433,"passed_time":0.7008717102,"remaining_time":0.9140400644},
{"learn":[4.039273327],"iteration":434,"passed_time":0.701971448,"remaining_time":0.9117560187},
{"learn":[4.035512024],"iteration":435,"passed_time":0.7028779446,"remaining_time":0.909227433},
{"learn":[4.034701087],"iteration":436,"passed_time":0.7038953196,"remaining_time":0.9068491189},
{"learn":[4.032000428],"iteration":437,"passed_time":0.7048173392,"remaining_time":0.9043546681},
{"learn":[4.029881072],"iteration":438,"passed_time":0.7057519825,"remaining_time":0.9018835129},
{"learn":[4.029136793],"iteration":439,"passed_time":0.7068317606,"remaining_time":0.8996040589},
{"learn":[4.028928742],"iteration":440,"passed_time":0.7077468379,"remaining_time":0.8971212752},
{"learn":[4.028630179],"iteration":441,"passed_time":0.7087498346,"remaining_time":0.8947565785},
{"learn":[4.024150689],"iteration":442,"passed_time":0.7097576478,"remaining_time":0.8924040854},
{"learn":[4.019415759],"iteration":443,"passed_time":0.710835262,"remaining_time":0.8901450578},
{"learn":[4.018788963],"iteration":444,"passed_time":0.7118761833,"remaining_time":0.8878455769},
{"learn":[4.01799828],"iteration":445,"passed_time":0.712846566,"remaining_time":0.8854641201},
{"learn":[4.015540482],"iteration":446,"passed_time":0.7139914105,"remaining_time":0.8833048099},
{"learn":[4.013455548],"iteration":447,"passed_time":0.714935611,"remaining_time":0.8809028064},
{"learn":[4.010234723],"iteration":448,"passed_time":0.7159841467,"remaining_time":0.8786353337},
{"learn":[4.008719653],"iteration":449,"passed_time":0.716979606,"remaining_time":0.8763084073},
{"learn":[4.008111539],"iteration":450,"passed_time":0.7178673133,"remaining_time":0.8738562195},
{"learn":[4.005077275],"iteration":451,"passed_time":0.7189369285,"remaining_time":0.8716314973},
{"learn":[4.003532712],"iteration":452,"passed_time":0.7200023466,"remaining_time":0.8694068071},
{"learn":[4.000075539],"iteration":453,"passed_time":0.7210105529,"remaining_time":0.8671184183},
{"learn":[3.997326575],"iteration":454,"passed_time":0.7221455515,"remaining_time":0.8649875287},
{"learn":[3.993549901],"iteration":455,"passed_time":0.7232218723,"remaining_time":0.8627910056},
{"learn":[3.988411821],"iteration":456,"passed_time":0.7243039902,"remaining_time":0.8606062728},
{"learn":[3.985318071],"iteration":457,"passed_time":0.7253256658,"remaining_time":0.8583548272},
{"learn":[3.982877941],"iteration":458,"passed_time":0.7263927481,"remaining_time":0.8561622586},
{"learn":[3.978642815],"iteration":459,"passed_time":0.7274950216,"remaining_time":0.854015895},
{"learn":[3.973360235],"iteration":460,"passed_time":0.7286117829,"remaining_time":0.851891},
{"learn":[3.969866768],"iteration":461,"passed_time":0.7297050748,"remaining_time":0.849743139},
{"learn":[3.967101801],"iteration":462,"passed_time":0.7306801292,"remaining_time":0.8474626985},
{"learn":[3.963946414],"iteration":463,"passed_time":0.7318334372,"remaining_time":0.8453937981},
{"learn":[3.961610362],"iteration":464,"passed_time":0.7328567,"remaining_time":0.8431792139},
{"learn":[3.959897668],"iteration":465,"passed_time":0.7339226831,"remaining_time":0.8410186969},
{"learn":[3.959259169],"iteration":466,"passed_time":0.7349294512,"remaining_time":0.8387952837},
{"learn":[3.956634376],"iteration":467,"passed_time":0.7359071553,"remaining_time":0.8365440313},
{"learn":[3.952081998],"iteration":468,"passed_time":0.7370127954,"remaining_time":0.8344430583},
{"learn":[3.951434882],"iteration":469,"passed_time":0.7380098303,"remaining_time":0.8322238511},
{"learn":[3.949861463],"iteration":470,"passed_time":0.7389354291,"remaining_time":0.8299296008},
{"learn":[3.948625103],"iteration":471,"passed_time":0.7399551483,"remaining_time":0.8277464371},
{"learn":[3.947387486],"iteration":472,"passed_time":0.7409248267,"remaining_time":0.8255124391},
{"learn":[3.94153363],"iteration":473,"passed_time":0.7420887129,"remaining_time":0.823499289},
{"learn":[3.940894241],"iteration":474,"passed_time":0.7432000708,"remaining_time":0.8214316572},
{"learn":[3.93914657],"iteration":475,"passed_time":0.744285505,"remaining_time":0.8193395055},
{"learn":[3.934024326],"iteration":476,"passed_time":0.7453885858,"remaining_time":0.8172709232},
{"learn":[3.932082492],"iteration":477,"passed_time":0.7464486431,"remaining_time":0.8151593969},
{"learn":[3.928387412],"iteration":478,"passed_time":0.7476349117,"remaining_time":0.8131895387},
{"learn":[3.925915863],"iteration":479,"passed_time":0.7486787342,"remaining_time":0.8110686287},
{"learn":[3.923238771],"iteration":480,"passed_time":0.7496485179,"remaining_time":0.8088723093},
{"learn":[3.921152752],"iteration":481,"passed_time":0.7506220971,"remaining_time":0.8066851583},
{"learn":[3.917876474],"iteration":482,"passed_time":0.7516584813,"remaining_time":0.8045702584},
{"learn":[3.915256099],"iteration":483,"passed_time":0.7526025491,"remaining_time":0.8023613954},
{"learn":[3.914334808],"iteration":484,"passed_time":0.7536504044,"remaining_time":0.8002679552},
{"learn":[3.911984521],"iteration":485,"passed_time":0.7546302567,"remaining_time":0.798106897},
{"learn":[3.911177238],"iteration":486,"passed_time":0.7555823577,"remaining_time":0.7959214569},
{"learn":[3.907248225],"iteration":487,"passed_time":0.7564716091,"remaining_time":0.7936751309},
{"learn":[3.905275216],"iteration":488,"passed_time":0.7573541049,"remaining_time":0.7914272957},
{"learn":[3.902805169],"iteration":489,"passed_time":0.7583871563,"remaining_time":0.7893417341},
{"learn":[3.900601743],"iteration":490,"passed_time":0.7593049213,"remaining_time":0.7871409469},
{"learn":[3.8989093],"iteration":491,"passed_time":0.7602897747,"remaining_time":0.7850146454},
{"learn":[3.894773999],"iteration":492,"passed_time":0.7614531507,"remaining_time":0.7830765667},
{"learn":[3.891017054],"iteration":493,"passed_time":0.7624392517,"remaining_time":0.7809600432},
{"learn":[3.887714297],"iteration":494,"passed_time":0.7634527905,"remaining_time":0.7788760792},
{"learn":[3.881945653],"iteration":495,"passed_time":0.7644305368,"remaining_time":0.7767600616},
{"learn":[3.879100021],"iteration":496,"passed_time":0.7653878802,"remaining_time":0.7746279754},
{"learn":[3.876608291],"iteration":497,"passed_time":0.7663895195,"remaining_time":0.7725452587},
{"learn":[3.874236874],"iteration":498,"passed_time":0.7673262315,"remaining_time":0.7704016874},
{"learn":[3.87391813],"iteration":499,"passed_time":0.7683301717,"remaining_time":0.7683301717},
{"learn":[3.871980623],"iteration":500,"passed_time":0.7693303519,"remaining_time":0.7662591729},
{"learn":[3.867079979],"iteration":501,"passed_time":0.7703714313,"remaining_time":0.7642330135},
{"learn":[3.863487539],"iteration":502,"passed_time":0.7713019429,"remaining_time":0.7621015221},
{"learn":[3.862457121],"iteration":503,"passed_time":0.772233119,"remaining_time":0.7599754504},
{"learn":[3.858979923],"iteration":504,"passed_time":0.7732140605,"remaining_time":0.757902891},
{"learn":[3.856343338],"iteration":505,"passed_time":0.7741901286,"remaining_time":0.7558298884},
{"learn":[3.853569169],"iteration":506,"passed_time":0.7750409059,"remaining_time":0.7536393819},
{"learn":[3.853221583],"iteration":507,"passed_time":0.776038879,"remaining_time":0.7515967096},
{"learn":[3.849681783],"iteration":508,"passed_time":0.7770556415,"remaining_time":0.7495762671},
{"learn":[3.84606927],"iteration":509,"passed_time":0.7779670255,"remaining_time":0.7474585147},
{"learn":[3.843461625],"iteration":510,"passed_time":0.7789301193,"remaining_time":0.7453949674},
{"learn":[3.84133826],"iteration":511,"passed_time":0.7798463656,"remaining_time":0.7432910672},
{"learn":[3.836854698],"iteration":512,"passed_time":0.7809784976,"remaining_time":0.7413967414},
{"learn":[3.835596214],"iteration":513,"passed_time":0.7820068508,"remaining_time":0.7394072559},
{"learn":[3.834588231],"iteration":514,"passed_time":0.7830468986,"remaining_time":0.7374325162},
{"learn":[3.832709914],"iteration":515,"passed_time":0.7840144414,"remaining_time":0.7353933907},
{"learn":[3.83224657],"iteration":516,"passed_time":0.7850280845,"remaining_time":0.7334014793},
{"learn":[3.829251455],"iteration":517,"passed_time":0.7860486789,"remaining_time":0.7314198132},
{"learn":[3.825044306],"iteration":518,"passed_time":0.7870642752,"remaining_time":0.7294372184},
{"learn":[3.8199986],"iteration":519,"passed_time":0.7880425725,"remaining_time":0.7274239131},
{"learn":[3.8177641],"iteration":520,"passed_time":0.7892251154,"remaining_time":0.7256023614},
{"learn":[3.815504965],"iteration":521,"passed_time":0.7903927,"remaining_time":0.7237695605},
{"learn":[3.812536915],"iteration":522,"passed_time":0.791374867,"remaining_time":0.7217701941},
{"learn":[3.810687108],"iteration":523,"passed_time":0.7923855482,"remaining_time":0.7198006124},
{"learn":[3.808778231],"iteration":524,"passed_time":0.7933971155,"remaining_time":0.7178354854},
{"learn":[3.806819091],"iteration":525,"passed_time":0.7944744554,"remaining_time":0.7159332545},
{"learn":[3.804686115],"iteration":526,"passed_time":0.7955307847,"remaining_time":0.7140152963},
{"learn":[3.803644019],"iteration":527,"passed_time":0.7966408728,"remaining_time":0.712148659},
{"learn":[3.800964434],"iteration":528,"passed_time":0.7976394485,"remaining_time":0.7101855959},
{"learn":[3.799151542],"iteration":529,"passed_time":0.7986568753,"remaining_time":0.7082428894},
{"learn":[3.796362209],"iteration":530,"passed_time":0.7996826967,"remaining_time":0.7063110824},
{"learn":[3.795253006],"iteration":531,"passed_time":0.8008296746,"remaining_time":0.7044892626},
{"learn":[3.793618727],"iteration":532,"passed_time":0.8018149004,"remaining_time":0.7025282523},
{"learn":[3.793434264],"iteration":533,"passed_time":0.8026121992,"remaining_time":0.7004069005},
{"learn":[3.792163523],"iteration":534,"passed_time":0.8036353558,"remaining_time":0.6984868046},
{"learn":[3.791977399],"iteration":535,"passed_time":0.804601764,"remaining_time":0.69652093},
{"learn":[3.788681939],"iteration":536,"passed_time":0.8056560806,"remaining_time":0.6946345723},
{"learn":[3.785283285],"iteration":537,"passed_time":0.8066738041,"remaining_time":0.6927198838},
{"learn":[3.783911032],"iteration":538,"passed_time":0.8077286229,"remaining_time":0.6908402507},
{"learn":[3.780326022],"iteration":539,"passed_time":0.8086935835,"remaining_time":0.6888871267},
{"learn":[3.777806732],"iteration":540,"passed_time":0.8096121754,"remaining_time":0.6868983152},
{"learn":[3.776876226],"iteration":541,"passed_time":0.810633747,"remaining_time":0.6850004726},
{"learn":[3.772206827],"iteration":542,"passed_time":0.8116696944,"remaining_time":0.6831179564},
{"learn":[3.768820504],"iteration":543,"passed_time":0.8126987648,"remaining_time":0.6812327881},
{"learn":[3.766913043],"iteration":544,"passed_time":0.8137190872,"remaining_time":0.6793434581},
{"learn":[3.765576749],"iteration":545,"passed_time":0.814738434,"remaining_time":0.6774565001},
{"learn":[3.763928388],"iteration":546,"passed_time":0.8157217656,"remaining_time":0.6755428881},
{"learn":[3.760475778],"iteration":547,"passed_time":0.8167899255,"remaining_time":0.6737026393},
{"learn":[3.758807191],"iteration":548,"passed_time":0.817744025,"remaining_time":0.6717715033},
{"learn":[3.755419431],"iteration":549,"passed_time":0.8187476146,"remaining_time":0.669884412},
{"learn":[3.755153747],"iteration":550,"passed_time":0.8196747887,"remaining_time":0.667938258},
{"learn":[3.753222829],"iteration":551,"passed_time":0.8205772587,"remaining_time":0.6659757462},
{"learn":[3.751978218],"iteration":552,"passed_time":0.821521876,"remaining_time":0.6640511367},
{"learn":[3.750086596],"iteration":553,"passed_time":0.8226119674,"remaining_time":0.6622471796},
{"learn":[3.746287197],"iteration":554,"passed_time":0.8235759747,"remaining_time":0.6603447004},
{"learn":[3.743744331],"iteration":555,"passed_time":0.8245888466,"remaining_time":0.6584846185},
{"learn":[3.740980135],"iteration":556,"passed_time":0.8254890383,"remaining_time":0.6565379605},
{"learn":[3.73684621],"iteration":557,"passed_time":0.826453559,"remaining_time":0.6546460091},
{"learn":[3.735850009],"iteration":558,"passed_time":0.8275303475,"remaining_time":0.652845945},
{"learn":[3.734253732],"iteration":559,"passed_time":0.8284217948,"remaining_time":0.6509028387},
{"learn":[3.733984129],"iteration":560,"passed_time":0.8292833727,"remaining_time":0.648940108},
{"learn":[3.731867289],"iteration":561,"passed_time":0.8301489512,"remaining_time":0.6469844139},
{"learn":[3.726743612],"iteration":562,"passed_time":0.8311304835,"remaining_time":0.6451225955},
{"learn":[3.723908329],"iteration":563,"passed_time":0.8321353828,"remaining_time":0.6432819626},
{"learn":[3.723705388],"iteration":564,"passed_time":0.8329813129,"remaining_time":0.6413218958},
{"learn":[3.721098243],"iteration":565,"passed_time":0.8340062137,"remaining_time":0.6395029978},
{"learn":[3.719610581],"iteration":566,"passed_time":0.8350515126,"remaining_time":0.6377024779},
{"learn":[3.715663796],"iteration":567,"passed_time":0.8360167536,"remaining_time":0.6358437281},
{"learn":[3.712633679],"iteration":568,"passed_time":0.8370453792,"remaining_time":0.6340361308},
{"learn":[3.711731219],"iteration":569,"passed_time":0.838124557,"remaining_time":0.6322694027},
{"learn":[3.708475681],"iteration":570,"passed_time":0.8390932618,"remaining_time":0.6304220828},
{"learn":[3.707985364],"iteration":571,"passed_time":0.8400212496,"remaining_time":0.6285473686},
{"learn":[3.705134561],"iteration":572,"passed_time":0.841052578,"remaining_time":0.6267529682},
{"learn":[3.703509064],"iteration":573,"passed_time":0.8420206036,"remaining_time":0.6249142459},
{"learn":[3.699070644],"iteration":574,"passed_time":0.8430127671,"remaining_time":0.6230963931},
{"learn":[3.696976795],"iteration":575,"passed_time":0.8439134967,"remaining_time":0.6212141017},
{"learn":[3.694261551],"iteration":576,"passed_time":0.844765829,"remaining_time":0.6192997325},
{"learn":[3.693349299],"iteration":577,"passed_time":0.8455718697,"remaining_time":0.6173552405},
{"learn":[3.691017284],"iteration":578,"passed_time":0.8464558687,"remaining_time":0.6154713657},
{"learn":[3.689895992],"iteration":579,"passed_time":0.847538042,"remaining_time":0.6137344442},
{"learn":[3.687882716],"iteration":580,"passed_time":0.848463784,"remaining_time":0.611886963},
{"learn":[3.686557981],"iteration":581,"passed_time":0.8494153359,"remaining_time":0.6100611863},
{"learn":[3.683362822],"iteration":582,"passed_time":0.8503058185,"remaining_time":0.6081947278},
{"learn":[3.68199861],"iteration":583,"passed_time":0.851232147,"remaining_time":0.6063571458},
{"learn":[3.681486367],"iteration":584,"passed_time":0.85214683,"remaining_time":0.6045144179},
{"learn":[3.6788087],"iteration":585,"passed_time":0.8532378774,"remaining_time":0.602799456},
{"learn":[3.678625667],"iteration":586,"passed_time":0.8543306594,"remaining_time":0.6010878404},
{"learn":[3.677367682],"iteration":587,"passed_time":0.8554635552,"remaining_time":0.5994064366},
{"learn":[3.675536829],"iteration":588,"passed_time":0.8565969888,"remaining_time":0.5977272706},
{"learn":[3.673393547],"iteration":589,"passed_time":0.8576838971,"remaining_time":0.5960176234},
{"learn":[3.672099744],"iteration":590,"passed_time":0.8588044859,"remaining_time":0.5943333921},
{"learn":[3.669898628],"iteration":591,"passed_time":0.8599512594,"remaining_time":0.5926691112},
{"learn":[3.666623722],"iteration":592,"passed_time":0.8609320584,"remaining_time":0.5908926607},
{"learn":[3.666482332],"iteration":593,"passed_time":0.8618711838,"remaining_time":0.5890904051},
{"learn":[3.662201944],"iteration":594,"passed_time":0.8629181594,"remaining_time":0.5873644614},
{"learn":[3.658276033],"iteration":595,"passed_time":0.8642137735,"remaining_time":0.5858093364},
{"learn":[3.65631272],"iteration":596,"passed_time":0.865273143,"remaining_time":0.5840956057},
{"learn":[3.654802065],"iteration":597,"passed_time":0.8662999422,"remaining_time":0.5823621685},
{"learn":[3.654265144],"iteration":598,"passed_time":0.8674422162,"remaining_time":0.5807083952},
{"learn":[3.652442886],"iteration":599,"passed_time":0.8684028399,"remaining_time":0.5789352266},
{"learn":[3.648429891],"iteration":600,"passed_time":0.8693266166,"remaining_time":0.5771402995},
{"learn":[3.646911886],"iteration":601,"passed_time":0.87042704,"remaining_time":0.575465053},
{"learn":[3.645507377],"iteration":602,"passed_time":0.8715579935,"remaining_time":0.5738118133},
{"learn":[3.643494608],"iteration":603,"passed_time":0.872579877,"remaining_time":0.5720887936},
{"learn":[3.641985228],"iteration":604,"passed_time":0.8736744403,"remaining_time":0.5704155437},
{"learn":[3.64053399],"iteration":605,"passed_time":0.8747816692,"remaining_time":0.5687524384},
{"learn":[3.636715905],"iteration":606,"passed_time":0.8758038321,"remaining_time":0.567036089},
{"learn":[3.635957245],"iteration":607,"passed_time":0.8768056613,"remaining_time":0.5653089132},
{"learn":[3.634170476],"iteration":608,"passed_time":0.877815663,"remaining_time":0.5635893666},
{"learn":[3.63159018],"iteration":609,"passed_time":0.8789185491,"remaining_time":0.5619315314},
{"learn":[3.629252622],"iteration":610,"passed_time":0.8800700633,"remaining_time":0.5603064724},
{"learn":[3.627069377],"iteration":611,"passed_time":0.8811201015,"remaining_time":0.5586186264},
{"learn":[3.624788821],"iteration":612,"passed_time":0.8822429195,"remaining_time":0.5569788089},
{"learn":[3.62312048],"iteration":613,"passed_time":0.8833759331,"remaining_time":0.555347085},
{"learn":[3.621692844],"iteration":614,"passed_time":0.8847361408,"remaining_time":0.5538592101},
{"learn":[3.618124235],"iteration":615,"passed_time":0.8858488776,"remaining_time":0.5522174822},
{"learn":[3.616718152],"iteration":616,"passed_time":0.8869401771,"remaining_time":0.5505641618},
{"learn":[3.614137254],"iteration":617,"passed_time":0.8878900333,"remaining_time":0.5488252309},
{"learn":[3.612244016],"iteration":618,"passed_time":0.888974563,"remaining_time":0.5471717423},
{"learn":[3.611173569],"iteration":619,"passed_time":0.889912192,"remaining_time":0.5454300532},
{"learn":[3.607512991],"iteration":620,"passed_time":0.8909704072,"remaining_time":0.543764548},
{"learn":[3.605314785],"iteration":621,"passed_time":0.8919277648,"remaining_time":0.5420397027},
{"learn":[3.603359051],"iteration":622,"passed_time":0.892999787,"remaining_time":0.540386709},
{"learn":[3.600556234],"iteration":623,"passed_time":0.8939205985,"remaining_time":0.5386444632},
{"learn":[3.598359307],"iteration":624,"passed_time":0.8948879675,"remaining_time":0.5369327805},
{"learn":[3.597019991],"iteration":625,"passed_time":0.8958767886,"remaining_time":0.5352362922},
{"learn":[3.593697937],"iteration":626,"passed_time":0.8968840193,"remaining_time":0.5335530131},
{"learn":[3.592478239],"iteration":627,"passed_time":0.8977725391,"remaining_time":0.5318015677},
{"learn":[3.591927416],"iteration":628,"passed_time":0.8987256092,"remaining_time":0.5300909396},
{"learn":[3.586799147],"iteration":629,"passed_time":0.8996699839,"remaining_time":0.5283776096},
{"learn":[3.586421984],"iteration":630,"passed_time":0.9006466966,"remaining_time":0.5266856277},
{"learn":[3.586263321],"iteration":631,"passed_time":0.9016586541,"remaining_time":0.5250164315},
{"learn":[3.583350914],"iteration":632,"passed_time":0.9025847811,"remaining_time":0.5232995492},
{"learn":[3.579048187],"iteration":633,"passed_time":0.9035971522,"remaining_time":0.521634949},
{"learn":[3.576761297],"iteration":634,"passed_time":0.9046102091,"remaining_time":0.5199727974},
{"learn":[3.573786136],"iteration":635,"passed_time":0.905646124,"remaining_time":0.5183257691},
{"learn":[3.573148707],"iteration":636,"passed_time":0.9066143295,"remaining_time":0.5166420747},
{"learn":[3.570612433],"iteration":637,"passed_time":0.9076168694,"remaining_time":0.5149801046},
{"learn":[3.568180686],"iteration":638,"passed_time":0.9086739661,"remaining_time":0.51335102},
{"learn":[3.56781226],"iteration":639,"passed_time":0.9097254402,"remaining_time":0.5117205601},
{"learn":[3.565897103],"iteration":640,"passed_time":0.9106660444,"remaining_time":0.5100298127},
{"learn":[3.562303834],"iteration":641,"passed_time":0.911600667,"remaining_time":0.5083380667},
{"learn":[3.560707371],"iteration":642,"passed_time":0.9125832232,"remaining_time":0.5066752888},
{"learn":[3.557764416],"iteration":643,"passed_time":0.9137150413,"remaining_time":0.5050971346},
{"learn":[3.55671183],"iteration":644,"passed_time":0.9145966027,"remaining_time":0.5033826263},
{"learn":[3.556218416],"iteration":645,"passed_time":0.9156391147,"remaining_time":0.5017588957},
{"learn":[3.552240561],"iteration":646,"passed_time":0.9166628127,"remaining_time":0.5001266969},
{"learn":[3.551552817],"iteration":647,"passed_time":0.9175445959,"remaining_time":0.4984192866},
{"learn":[3.54824755],"iteration":648,"passed_time":0.9185553704,"remaining_time":0.4967841834},
{"learn":[3.546228049],"iteration":649,"passed_time":0.9195512645,"remaining_time":0.4951429886},
{"learn":[3.545818341],"iteration":650,"passed_time":0.9204065948,"remaining_time":0.4934284203},
{"learn":[3.544012207],"iteration":651,"passed_time":0.9215077331,"remaining_time":0.4918476858},
{"learn":[3.541954921],"iteration":652,"passed_time":0.9226559177,"remaining_time":0.4902934203},
{"learn":[3.540527585],"iteration":653,"passed_time":0.9236131961,"remaining_time":0.4886393973},
{"learn":[3.537693948],"iteration":654,"passed_time":0.9248059091,"remaining_time":0.4871115094},
{"learn":[3.536425814],"iteration":655,"passed_time":0.9257403576,"remaining_time":0.4854492119},
{"learn":[3.534450051],"iteration":656,"passed_time":0.9267466922,"remaining_time":0.4838266597},
{"learn":[3.533588325],"iteration":657,"passed_time":0.9276349296,"remaining_time":0.4821445987},
{"learn":[3.532343013],"iteration":658,"passed_time":0.9286749771,"remaining_time":0.480543501},
{"learn":[3.530261333],"iteration":659,"passed_time":0.9298701051,"remaining_time":0.4790239935},
{"learn":[3.526464618],"iteration":660,"passed_time":0.9309694965,"remaining_time":0.4774563681},
{"learn":[3.525589233],"iteration":661,"passed_time":0.9320133643,"remaining_time":0.4758618084},
{"learn":[3.522774912],"iteration":662,"passed_time":0.9331478109,"remaining_time":0.4743149506},
{"learn":[3.519289606],"iteration":663,"passed_time":0.9342121012,"remaining_time":0.4727338343},
{"learn":[3.518529085],"iteration":664,"passed_time":0.9352390743,"remaining_time":0.4711354735},
{"learn":[3.516094087],"iteration":665,"passed_time":0.9362356038,"remaining_time":0.469523561},
{"learn":[3.514627065],"iteration":666,"passed_time":0.9373126411,"remaining_time":0.4679536874},
{"learn":[3.513543173],"iteration":667,"passed_time":0.9382768994,"remaining_time":0.4663292374},
{"learn":[3.511374621],"iteration":668,"passed_time":0.9392109057,"remaining_time":0.4646917934},
{"learn":[3.511149314],"iteration":669,"passed_time":0.9403062409,"remaining_time":0.4631359097},
{"learn":[3.510173352],"iteration":670,"passed_time":0.9414873398,"remaining_time":0.4616234498},
{"learn":[3.507852257],"iteration":671,"passed_time":0.9424908866,"remaining_time":0.4600253137},
{"learn":[3.505950733],"iteration":672,"passed_time":0.9436500151,"remaining_time":0.4585045393},
{"learn":[3.501933208],"iteration":673,"passed_time":0.9446650407,"remaining_time":0.4569151384},
{"learn":[3.498898474],"iteration":674,"passed_time":0.9456436499,"remaining_time":0.4553099055},
{"learn":[3.497476568],"iteration":675,"passed_time":0.9465072077,"remaining_time":0.4536513836},
{"learn":[3.496151405],"iteration":676,"passed_time":0.9474856982,"remaining_time":0.4520500451},
{"learn":[3.495726787],"iteration":677,"passed_time":0.9484479152,"remaining_time":0.4504428152},
{"learn":[3.494032072],"iteration":678,"passed_time":0.9494543666,"remaining_time":0.4488583972},
{"learn":[3.490758369],"iteration":679,"passed_time":0.9505744104,"remaining_time":0.4473291343},
{"learn":[3.487905891],"iteration":680,"passed_time":0.9515266601,"remaining_time":0.4457224737},
{"learn":[3.484974886],"iteration":681,"passed_time":0.9525800687,"remaining_time":0.4441649001},
{"learn":[3.483585902],"iteration":682,"passed_time":0.9537136664,"remaining_time":0.4426460209},
{"learn":[3.480359166],"iteration":683,"passed_time":0.9547071333,"remaining_time":0.4410635294},
{"learn":[3.477203515],"iteration":684,"passed_time":0.9556573265,"remaining_time":0.4394628582},
{"learn":[3.475887256],"iteration":685,"passed_time":0.9566040734,"remaining_time":0.4378625059},
{"learn":[3.475674655],"iteration":686,"passed_time":0.9575200126,"remaining_time":0.4362500203},
{"learn":[3.472646113],"iteration":687,"passed_time":0.9584883505,"remaining_time":0.4346633217},
{"learn":[3.467488119],"iteration":688,"passed_time":0.9596901619,"remaining_time":0.4331838031},
{"learn":[3.4642353],"iteration":689,"passed_time":0.9608108315,"remaining_time":0.4316686344},
{"learn":[3.461445229],"iteration":690,"passed_time":0.9617800158,"remaining_time":0.4300868667},
{"learn":[3.461232432],"iteration":691,"passed_time":0.9626073639,"remaining_time":0.42844374},
{"learn":[3.46093574],"iteration":692,"passed_time":0.9634963543,"remaining_time":0.4268302753},
{"learn":[3.460004441],"iteration":693,"passed_time":0.9643340981,"remaining_time":0.4251963026},
{"learn":[3.457972032],"iteration":694,"passed_time":0.96529567,"remaining_time":0.4236189631},
{"learn":[3.456590857],"iteration":695,"passed_time":0.9664076405,"remaining_time":0.4221090843},
{"learn":[3.456418395],"iteration":696,"passed_time":0.9674688633,"remaining_time":0.4205782863},
{"learn":[3.45473614],"iteration":697,"passed_time":0.9684317382,"remaining_time":0.4190062821},
{"learn":[3.452437454],"iteration":698,"passed_time":0.9694413485,"remaining_time":0.4174561458},
{"learn":[3.449921645],"iteration":699,"passed_time":0.9704859103,"remaining_time":0.415922533},
{"learn":[3.448457055],"iteration":700,"passed_time":0.9715339419,"remaining_time":0.4143917955},
{"learn":[3.446793321],"iteration":701,"passed_time":0.9725651763,"remaining_time":0.4128553028},
{"learn":[3.445841147],"iteration":702,"passed_time":0.9735920956,"remaining_time":0.4113184245},
{"learn":[3.443547651],"iteration":703,"passed_time":0.9747046052,"remaining_time":0.4098189817},
{"learn":[3.442294019],"iteration":704,"passed_time":0.9756523029,"remaining_time":0.4082516728},
{"learn":[3.439179317],"iteration":705,"passed_time":0.9766206024,"remaining_time":0.4066946985},
{"learn":[3.438984523],"iteration":706,"passed_time":0.977617757,"remaining_time":0.4051513477},
{"learn":[3.437475308],"iteration":707,"passed_time":0.9786399009,"remaining_time":0.4036198461},
{"learn":[3.434877074],"iteration":708,"passed_time":0.9796121637,"remaining_time":0.4020693084},
{"learn":[3.432578598],"iteration":709,"passed_time":0.9806435629,"remaining_time":0.4005445539},
{"learn":[3.432176973],"iteration":710,"passed_time":0.9816998005,"remaining_time":0.3990312832},
{"learn":[3.431511317],"iteration":711,"passed_time":0.982673822,"remaining_time":0.3974860404},
{"learn":[3.430192504],"iteration":712,"passed_time":0.9837395734,"remaining_time":0.3959793234},
{"learn":[3.427514523],"iteration":713,"passed_time":0.9847746587,"remaining_time":0.394461558},
{"learn":[3.424797069],"iteration":714,"passed_time":0.9858245257,"remaining_time":0.3929510347},
{"learn":[3.423052681],"iteration":715,"passed_time":0.9868185314,"remaining_time":0.3914196409},
{"learn":[3.42193426],"iteration":716,"passed_time":0.9878395648,"remaining_time":0.389900414},
{"learn":[3.420805232],"iteration":717,"passed_time":0.9888855087,"remaining_time":0.3883923586},
{"learn":[3.417339743],"iteration":718,"passed_time":0.9900728994,"remaining_time":0.3869408689},
{"learn":[3.416162056],"iteration":719,"passed_time":0.9910214011,"remaining_time":0.3853972116},
{"learn":[3.413953322],"iteration":720,"passed_time":0.9920738029,"remaining_time":0.3838954106},
{"learn":[3.413629584],"iteration":721,"passed_time":0.9929610258,"remaining_time":0.3823312537},
{"learn":[3.411603238],"iteration":722,"passed_time":0.9938939052,"remaining_time":0.3807864616},
{"learn":[3.409318534],"iteration":723,"passed_time":0.9949619168,"remaining_time":0.3792948743},
{"learn":[3.405641817],"iteration":724,"passed_time":0.9959605028,"remaining_time":0.3777781217},
{"learn":[3.405094314],"iteration":725,"passed_time":0.9969350676,"remaining_time":0.3762537308},
{"learn":[3.404563997],"iteration":726,"passed_time":0.997895916,"remaining_time":0.3747257016},
{"learn":[3.4019162],"iteration":727,"passed_time":0.9988998683,"remaining_time":0.3732153354},
{"learn":[3.401307733],"iteration":728,"passed_time":0.9998293442,"remaining_time":0.3716786725},
{"learn":[3.398501756],"iteration":729,"passed_time":1.000871253,"remaining_time":0.3701852578},
{"learn":[3.397572376],"iteration":730,"passed_time":1.001837703,"remaining_time":0.3686653107},
{"learn":[3.394774578],"iteration":731,"passed_time":1.002756858,"remaining_time":0.3671295601},
{"learn":[3.390794784],"iteration":732,"passed_time":1.003768418,"remaining_time":0.3656291508},
{"learn":[3.387900384],"iteration":733,"passed_time":1.004806449,"remaining_time":0.3641396669},
{"learn":[3.387352142],"iteration":734,"passed_time":1.00577573,"remaining_time":0.3626266236},
{"learn":[3.384202526],"iteration":735,"passed_time":1.006787885,"remaining_time":0.3611304369},
{"learn":[3.383184922],"iteration":736,"passed_time":1.007819684,"remaining_time":0.3596425739},
{"learn":[3.381013917],"iteration":737,"passed_time":1.008772543,"remaining_time":0.3581279219},
{"learn":[3.378755901],"iteration":738,"passed_time":1.00976574,"remaining_time":0.3566290367},
{"learn":[3.375390532],"iteration":739,"passed_time":1.010710948,"remaining_time":0.3551146573},
{"learn":[3.375208778],"iteration":740,"passed_time":1.011630098,"remaining_time":0.3535927063},
{"learn":[3.373562953],"iteration":741,"passed_time":1.012695958,"remaining_time":0.3521233925},
{"learn":[3.370794216],"iteration":742,"passed_time":1.01364068,"remaining_time":0.3506132634},
{"learn":[3.367954742],"iteration":743,"passed_time":1.014594926,"remaining_time":0.3491079316},
{"learn":[3.367623734],"iteration":744,"passed_time":1.015584212,"remaining_time":0.3476160726},
{"learn":[3.364476756],"iteration":745,"passed_time":1.016846605,"remaining_time":0.3462185491},
{"learn":[3.361433046],"iteration":746,"passed_time":1.017887795,"remaining_time":0.3447464686},
{"learn":[3.359175437],"iteration":747,"passed_time":1.018896282,"remaining_time":0.3432645227},
{"learn":[3.357475045],"iteration":748,"passed_time":1.019900065,"remaining_time":0.3417822646},
{"learn":[3.355395452],"iteration":749,"passed_time":1.020907496,"remaining_time":0.3403024987},
{"learn":[3.353278344],"iteration":750,"passed_time":1.021860551,"remaining_time":0.3388059615},
{"learn":[3.353109374],"iteration":751,"passed_time":1.022736477,"remaining_time":0.3372854341},
{"learn":[3.351707042],"iteration":752,"passed_time":1.023784312,"remaining_time":0.3358230082},
{"learn":[3.350270271],"iteration":753,"passed_time":1.024858899,"remaining_time":0.33437041},
{"learn":[3.349799526],"iteration":754,"passed_time":1.025765441,"remaining_time":0.3328642821},
{"learn":[3.347239419],"iteration":755,"passed_time":1.026837577,"remaining_time":0.3314131863},
{"learn":[3.345845465],"iteration":756,"passed_time":1.027839368,"remaining_time":0.3299405105},
{"learn":[3.344787519],"iteration":757,"passed_time":1.028812087,"remaining_time":0.3284597956},
{"learn":[3.342297245],"iteration":758,"passed_time":1.029939273,"remaining_time":0.3270294661},
{"learn":[3.341975131],"iteration":759,"passed_time":1.030898899,"remaining_time":0.3255470207},
{"learn":[3.339124298],"iteration":760,"passed_time":1.031859622,"remaining_time":0.324066294},
{"learn":[3.338908053],"iteration":761,"passed_time":1.032872291,"remaining_time":0.3226031565},
{"learn":[3.33729174],"iteration":762,"passed_time":1.033954661,"remaining_time":0.3211628501},
{"learn":[3.334627792],"iteration":763,"passed_time":1.034927731,"remaining_time":0.3196897178},
{"learn":[3.331571992],"iteration":764,"passed_time":1.035872765,"remaining_time":0.3182092808},
{"learn":[3.32968905],"iteration":765,"passed_time":1.036912106,"remaining_time":0.3167590507},
{"learn":[3.327600985],"iteration":766,"passed_time":1.037900748,"remaining_time":0.3152944907},
{"learn":[3.326274809],"iteration":767,"passed_time":1.038872639,"remaining_time":0.3138261096},
{"learn":[3.326180472],"iteration":768,"passed_time":1.039876171,"remaining_time":0.3123685246},
{"learn":[3.322572868],"iteration":769,"passed_time":1.040946928,"remaining_time":0.3109321993},
{"learn":[3.320792144],"iteration":770,"passed_time":1.041887705,"remaining_time":0.3094582159},
{"learn":[3.319048303],"iteration":771,"passed_time":1.042994052,"remaining_time":0.3080345127},
{"learn":[3.316727786],"iteration":772,"passed_time":1.043989742,"remaining_time":0.3065791352},
{"learn":[3.314510969],"iteration":773,"passed_time":1.044937327,"remaining_time":0.3051108992},
{"learn":[3.311499521],"iteration":774,"passed_time":1.045868792,"remaining_time":0.3036393267},
{"learn":[3.30966478],"iteration":775,"passed_time":1.046824239,"remaining_time":0.3021760689},
{"learn":[3.307735162],"iteration":776,"passed_time":1.047892055,"remaining_time":0.3007463683},
{"learn":[3.306213025],"iteration":777,"passed_time":1.048955186,"remaining_time":0.2993162614},
{"learn":[3.303325458],"iteration":778,"passed_time":1.049948145,"remaining_time":0.2978671888},
{"learn":[3.302523492],"iteration":779,"passed_time":1.050914142,"remaining_time":0.2964116811},
{"learn":[3.300714856],"iteration":780,"passed_time":1.052007064,"remaining_time":0.294993018},
{"learn":[3.298960434],"iteration":781,"passed_time":1.053031043,"remaining_time":0.2935559686},
{"learn":[3.297430478],"iteration":782,"passed_time":1.053977185,"remaining_time":0.2920984025},
{"learn":[3.296310043],"iteration":783,"passed_time":1.054915045,"remaining_time":0.2906398593},
{"learn":[3.294652527],"iteration":784,"passed_time":1.05598186,"remaining_time":0.2892179617},
{"learn":[3.293081686],"iteration":785,"passed_time":1.057001522,"remaining_time":0.2877841293},
{"learn":[3.292074899],"iteration":786,"passed_time":1.057974001,"remaining_time":0.2863385797},
{"learn":[3.290117848],"iteration":787,"passed_time":1.0588578,"remaining_time":0.2848703725},
{"learn":[3.28994569],"iteration":788,"passed_time":1.059808144,"remaining_time":0.2834214429},
{"learn":[3.287682298],"iteration":789,"passed_time":1.060876296,"remaining_time":0.2820050914},
{"learn":[3.285435393],"iteration":790,"passed_time":1.061830971,"remaining_time":0.2805596371},
{"learn":[3.284695325],"iteration":791,"passed_time":1.062754091,"remaining_time":0.279107135},
{"learn":[3.283269413],"iteration":792,"passed_time":1.063832071,"remaining_time":0.2776963919},
{"learn":[3.282072432],"iteration":793,"passed_time":1.06493124,"remaining_time":0.2762919841},
{"learn":[3.281110702],"iteration":794,"passed_time":1.066007631,"remaining_time":0.2748824709},
{"learn":[3.280767022],"iteration":795,"passed_time":1.067132737,"remaining_time":0.2734862794},
{"learn":[3.278986948],"iteration":796,"passed_time":1.068262798,"remaining_time":0.2720920302},
{"learn":[3.277448287],"iteration":797,"passed_time":1.069335414,"remaining_time":0.2706839018},
{"learn":[3.27562372],"iteration":798,"passed_time":1.070355005,"remaining_time":0.269263274},
{"learn":[3.27449006],"iteration":799,"passed_time":1.071431733,"remaining_time":0.2678579332},
{"learn":[3.272149311],"iteration":800,"passed_time":1.072494296,"remaining_time":0.2664498938},
{"learn":[3.269572595],"iteration":801,"passed_time":1.073501399,"remaining_time":0.2650290237},
{"learn":[3.268072374],"iteration":802,"passed_time":1.074614958,"remaining_time":0.263635301},
{"learn":[3.264636682],"iteration":803,"passed_time":1.075533938,"remaining_time":0.2621948407},
{"learn":[3.262680371],"iteration":804,"passed_time":1.076527424,"remaining_time":0.2607737238},
{"learn":[3.261347727],"iteration":805,"passed_time":1.077464353,"remaining_time":0.2593400551},
{"learn":[3.258875705],"iteration":806,"passed_time":1.078319371,"remaining_time":0.2578880281},
{"learn":[3.256530567],"iteration":807,"passed_time":1.079331911,"remaining_time":0.2564749096},
{"learn":[3.254544575],"iteration":808,"passed_time":1.080304458,"remaining_time":0.2550533392},
{"learn":[3.25444741],"iteration":809,"passed_time":1.081173635,"remaining_time":0.2536086305},
{"learn":[3.253749441],"iteration":810,"passed_time":1.082089063,"remaining_time":0.2521761195},
{"learn":[3.251092637],"iteration":811,"passed_time":1.082996561,"remaining_time":0.2507430462},
{"learn":[3.250544552],"iteration":812,"passed_time":1.083920186,"remaining_time":0.2493149751},
{"learn":[3.249018155],"iteration":813,"passed_time":1.084950358,"remaining_time":0.2479124896},
{"learn":[3.248671245],"iteration":814,"passed_time":1.085885216,"remaining_time":0.2464892822},
{"learn":[3.247899951],"iteration":815,"passed_time":1.086865938,"remaining_time":0.2450776135},
{"learn":[3.245182087],"iteration":816,"passed_time":1.087790595,"remaining_time":0.2436544418},
{"learn":[3.243874059],"iteration":817,"passed_time":1.088789905,"remaining_time":0.2422490986},
{"learn":[3.240271144],"iteration":818,"passed_time":1.089752397,"remaining_time":0.2408366103},
{"learn":[3.238803488],"iteration":819,"passed_time":1.090726173,"remaining_time":0.2394276966},
{"learn":[3.236737582],"iteration":820,"passed_time":1.091762893,"remaining_time":0.2380335662},
{"learn":[3.236612635],"iteration":821,"passed_time":1.092652754,"remaining_time":0.2366085038},
{"learn":[3.235995145],"iteration":822,"passed_time":1.093584601,"remaining_time":0.235193772},
{"learn":[3.23591238],"iteration":823,"passed_time":1.09455983,"remaining_time":0.2337894782},
{"learn":[3.232151854],"iteration":824,"passed_time":1.095679378,"remaining_time":0.2324168378},
{"learn":[3.228420981],"iteration":825,"passed_time":1.096768094,"remaining_time":0.2310383153},
{"learn":[3.226864915],"iteration":826,"passed_time":1.097762494,"remaining_time":0.2296407636},
{"learn":[3.226350891],"iteration":827,"passed_time":1.098831329,"remaining_time":0.2282596481},
{"learn":[3.224000169],"iteration":828,"passed_time":1.099809641,"remaining_time":0.2268606135},
{"learn":[3.223559343],"iteration":829,"passed_time":1.10084348,"remaining_time":0.2254739657},
{"learn":[3.223472045],"iteration":830,"passed_time":1.101798052,"remaining_time":0.2240720466},
{"learn":[3.221539124],"iteration":831,"passed_time":1.102741992,"remaining_time":0.2226690561},
{"learn":[3.220198949],"iteration":832,"passed_time":1.103683562,"remaining_time":0.2212666926},
{"learn":[3.218090929],"iteration":833,"passed_time":1.104698868,"remaining_time":0.2198801104},
{"learn":[3.216707723],"iteration":834,"passed_time":1.105717488,"remaining_time":0.2184950726},
{"learn":[3.216359816],"iteration":835,"passed_time":1.106663337,"remaining_time":0.2170966355},
{"learn":[3.215034495],"iteration":836,"passed_time":1.107653075,"remaining_time":0.215707827},
{"learn":[3.21431621],"iteration":837,"passed_time":1.108572494,"remaining_time":0.214306377},
{"learn":[3.21355388],"iteration":838,"passed_time":1.109502594,"remaining_time":0.2129081258},
{"learn":[3.211689264],"iteration":839,"passed_time":1.110379958,"remaining_time":0.2115009444},
{"learn":[3.211616065],"iteration":840,"passed_time":1.111189683,"remaining_time":0.2100822349},
{"learn":[3.208568464],"iteration":841,"passed_time":1.112245206,"remaining_time":0.2087110957},
{"learn":[3.207963005],"iteration":842,"passed_time":1.113230462,"remaining_time":0.2073276187},
{"learn":[3.206667528],"iteration":843,"passed_time":1.114145427,"remaining_time":0.2059320931},
{"learn":[3.206516714],"iteration":844,"passed_time":1.115042772,"remaining_time":0.204534473},
{"learn":[3.202750324],"iteration":845,"passed_time":1.115966579,"remaining_time":0.2031428524},
{"learn":[3.20265018],"iteration":846,"passed_time":1.116870425,"remaining_time":0.2017487308},
{"learn":[3.202559063],"iteration":847,"passed_time":1.117853737,"remaining_time":0.2003700095},
{"learn":[3.19964563],"iteration":848,"passed_time":1.118911742,"remaining_time":0.1990055042},
{"learn":[3.197315389],"iteration":849,"passed_time":1.119801978,"remaining_time":0.1976121138},
{"learn":[3.194748598],"iteration":850,"passed_time":1.120805691,"remaining_time":0.1962397744},
{"learn":[3.194674889],"iteration":851,"passed_time":1.121773386,"remaining_time":0.1948620436},
{"learn":[3.191797173],"iteration":852,"passed_time":1.122932318,"remaining_time":0.1935182306},
{"learn":[3.189835943],"iteration":853,"passed_time":1.123836814,"remaining_time":0.1921313522},
{"learn":[3.186400584],"iteration":854,"passed_time":1.124755953,"remaining_time":0.1907480856},
{"learn":[3.18420526],"iteration":855,"passed_time":1.12566967,"remaining_time":0.1893649913},
{"learn":[3.182778061],"iteration":856,"passed_time":1.126580273,"remaining_time":0.1879824727},
{"learn":[3.180353729],"iteration":857,"passed_time":1.127588037,"remaining_time":0.1866171344},
{"learn":[3.175999783],"iteration":858,"passed_time":1.128668081,"remaining_time":0.185264493},
{"learn":[3.174441423],"iteration":859,"passed_time":1.129714581,"remaining_time":0.1839070248},
{"learn":[3.172536559],"iteration":860,"passed_time":1.130644656,"remaining_time":0.1825314834},
{"learn":[3.17075245],"iteration":861,"passed_time":1.131645426,"remaining_time":0.1811682932},
{"learn":[3.169756667],"iteration":862,"passed_time":1.13252939,"remaining_time":0.1797874003},
{"learn":[3.166752746],"iteration":863,"passed_time":1.133433362,"remaining_time":0.1784108069},
{"learn":[3.165100055],"iteration":864,"passed_time":1.134312021,"remaining_time":0.1770313558},
{"learn":[3.164965324],"iteration":865,"passed_time":1.135190833,"remaining_time":0.175653085},
{"learn":[3.163265293],"iteration":866,"passed_time":1.136078599,"remaining_time":0.1742773398},
{"learn":[3.162356424],"iteration":867,"passed_time":1.136955767,"remaining_time":0.1729011075},
{"learn":[3.162198852],"iteration":868,"passed_time":1.137873247,"remaining_time":0.1715321005},
{"learn":[3.162124158],"iteration":869,"passed_time":1.13855332,"remaining_time":0.1701286569},
{"learn":[3.16062536],"iteration":870,"passed_time":1.139528007,"remaining_time":0.1687705085},
{"learn":[3.157958186],"iteration":871,"passed_time":1.140463605,"remaining_time":0.1674075016},
{"learn":[3.156293236],"iteration":872,"passed_time":1.141274431,"remaining_time":0.1660273228},
{"learn":[3.15369826],"iteration":873,"passed_time":1.142187275,"remaining_time":0.164663154},
{"learn":[3.151738136],"iteration":874,"passed_time":1.143135778,"remaining_time":0.1633051112},
{"learn":[3.149143575],"iteration":875,"passed_time":1.144077618,"remaining_time":0.1619470601},
{"learn":[3.14853823],"iteration":876,"passed_time":1.145052326,"remaining_time":0.1605945679},
{"learn":[3.146066414],"iteration":877,"passed_time":1.145973987,"remaining_time":0.1592355654},
{"learn":[3.14359318],"iteration":878,"passed_time":1.14688194,"remaining_time":0.1578756709},
{"learn":[3.142295521],"iteration":879,"passed_time":1.147859177,"remaining_time":0.1565262515},
{"learn":[3.138720449],"iteration":880,"passed_time":1.148782137,"remaining_time":0.1551703455},
{"learn":[3.137811926],"iteration":881,"passed_time":1.149775908,"remaining_time":0.1538248948},
{"learn":[3.134669975],"iteration":882,"passed_time":1.150693963,"remaining_time":0.1524702079},
{"learn":[3.134380189],"iteration":883,"passed_time":1.15163894,"remaining_time":0.1511200419},
{"learn":[3.132972196],"iteration":884,"passed_time":1.152534216,"remaining_time":0.1497643332},
{"learn":[3.129885903],"iteration":885,"passed_time":1.153381757,"remaining_time":0.1484035218},
{"learn":[3.128549057],"iteration":886,"passed_time":1.154310377,"remaining_time":0.1470541969},
{"learn":[3.127843245],"iteration":887,"passed_time":1.155296624,"remaining_time":0.1457130877},
{"learn":[3.12465034],"iteration":888,"passed_time":1.156193467,"remaining_time":0.144361614},
{"learn":[3.122290946],"iteration":889,"passed_time":1.157094649,"remaining_time":0.1430116982},
{"learn":[3.121554033],"iteration":890,"passed_time":1.158005904,"remaining_time":0.141664022},
{"learn":[3.119500893],"iteration":891,"passed_time":1.15895792,"remaining_time":0.1403222594},
{"learn":[3.118745194],"iteration":892,"passed_time":1.159846914,"remaining_time":0.1389738184},
{"learn":[3.118459931],"iteration":893,"passed_time":1.160776279,"remaining_time":0.1376311919},
{"learn":[3.116267047],"iteration":894,"passed_time":1.161746596,"remaining_time":0.1362942933},
{"learn":[3.115184347],"iteration":895,"passed_time":1.162750402,"remaining_time":0.1349621003},
{"learn":[3.113482931],"iteration":896,"passed_time":1.163721707,"remaining_time":0.1336269073},
{"learn":[3.112570214],"iteration":897,"passed_time":1.164720026,"remaining_time":0.1322955931},
{"learn":[3.111917425],"iteration":898,"passed_time":1.165651989,"remaining_time":0.1309575649},
{"learn":[3.109744084],"iteration":899,"passed_time":1.16662546,"remaining_time":0.1296250511},
{"learn":[3.108518985],"iteration":900,"passed_time":1.167470087,"remaining_time":0.1282791772},
{"learn":[3.107060209],"iteration":901,"passed_time":1.168399262,"remaining_time":0.1269436006},
{"learn":[3.10535444],"iteration":902,"passed_time":1.169420864,"remaining_time":0.1256188525},
{"learn":[3.103980262],"iteration":903,"passed_time":1.170308201,"remaining_time":0.1242805169},
{"learn":[3.100984761],"iteration":904,"passed_time":1.171104738,"remaining_time":0.1229336465},
{"learn":[3.09930519],"iteration":905,"passed_time":1.172032645,"remaining_time":0.121601621},
{"learn":[3.098008211],"iteration":906,"passed_time":1.172879314,"remaining_time":0.1202621568},
{"learn":[3.096579399],"iteration":907,"passed_time":1.173913914,"remaining_time":0.1189428194},
{"learn":[3.09487955],"iteration":908,"passed_time":1.174891866,"remaining_time":0.1176184377},
{"learn":[3.093882565],"iteration":909,"passed_time":1.175885942,"remaining_time":0.1162964119},
{"learn":[3.092496512],"iteration":910,"passed_time":1.176888935,"remaining_time":0.1149759772},
{"learn":[3.091175642],"iteration":911,"passed_time":1.178002032,"remaining_time":0.1136668627},
{"learn":[3.088159821],"iteration":912,"passed_time":1.179074788,"remaining_time":0.1123543336},
{"learn":[3.085139982],"iteration":913,"passed_time":1.180050789,"remaining_time":0.1110332252},
{"learn":[3.083422746],"iteration":914,"passed_time":1.18105684,"remaining_time":0.1097156628},
{"learn":[3.081752299],"iteration":915,"passed_time":1.181937508,"remaining_time":0.1083872824},
{"learn":[3.08057662],"iteration":916,"passed_time":1.182910905,"remaining_time":0.1070682717},
{"learn":[3.079371069],"iteration":917,"passed_time":1.183835516,"remaining_time":0.1057456561},
{"learn":[3.078658744],"iteration":918,"passed_time":1.184774898,"remaining_time":0.1044252086},
{"learn":[3.077206418],"iteration":919,"passed_time":1.185689713,"remaining_time":0.1031034533},
{"learn":[3.076528475],"iteration":920,"passed_time":1.186680632,"remaining_time":0.1017891096},
{"learn":[3.07461814],"iteration":921,"passed_time":1.187607476,"remaining_time":0.1004700468},
{"learn":[3.073815771],"iteration":922,"passed_time":1.188591752,"remaining_time":0.09915662505},
{"learn":[3.071955811],"iteration":923,"passed_time":1.189460871,"remaining_time":0.09783444389},
{"learn":[3.069667267],"iteration":924,"passed_time":1.190343976,"remaining_time":0.09651437643},
{"learn":[3.069374583],"iteration":925,"passed_time":1.191382294,"remaining_time":0.09520765629},
{"learn":[3.069085277],"iteration":926,"passed_time":1.19227169,"remaining_time":0.0938897879},
{"learn":[3.066430992],"iteration":927,"passed_time":1.193266644,"remaining_time":0.09258103273},
{"learn":[3.065716755],"iteration":928,"passed_time":1.194182337,"remaining_time":0.09126689549},
{"learn":[3.063695656],"iteration":929,"passed_time":1.195150361,"remaining_time":0.08995755406},
{"learn":[3.061763853],"iteration":930,"passed_time":1.196115234,"remaining_time":0.08864871231},
{"learn":[3.059721236],"iteration":931,"passed_time":1.19699427,"remaining_time":0.08733434585},
{"learn":[3.058039568],"iteration":932,"passed_time":1.197885903,"remaining_time":0.08602181727},
{"learn":[3.055445373],"iteration":933,"passed_time":1.199011868,"remaining_time":0.08472674872},
{"learn":[3.055191977],"iteration":934,"passed_time":1.19990312,"remaining_time":0.0834157249},
{"learn":[3.052927103],"iteration":935,"passed_time":1.200801413,"remaining_time":0.08210607955},
{"learn":[3.051512167],"iteration":936,"passed_time":1.201800416,"remaining_time":0.08080408346},
{"learn":[3.051468506],"iteration":937,"passed_time":1.202706983,"remaining_time":0.07949662363},
{"learn":[3.048715663],"iteration":938,"passed_time":1.203686891,"remaining_time":0.07819478204},
{"learn":[3.048587736],"iteration":939,"passed_time":1.204575678,"remaining_time":0.07688780921},
{"learn":[3.046675631],"iteration":940,"passed_time":1.205508457,"remaining_time":0.0755844835},
{"learn":[3.046021395],"iteration":941,"passed_time":1.206433444,"remaining_time":0.0742814647},
{"learn":[3.043046219],"iteration":942,"passed_time":1.207471477,"remaining_time":0.07298608079},
{"learn":[3.04042614],"iteration":943,"passed_time":1.208408009,"remaining_time":0.07168522086},
{"learn":[3.039204763],"iteration":944,"passed_time":1.20929077,"remaining_time":0.07038200247},
{"learn":[3.038331453],"iteration":945,"passed_time":1.21030808,"remaining_time":0.06908735341},
{"learn":[3.03725926],"iteration":946,"passed_time":1.211330245,"remaining_time":0.06779356174},
{"learn":[3.035143259],"iteration":947,"passed_time":1.212277564,"remaining_time":0.06649623769},
{"learn":[3.033118641],"iteration":948,"passed_time":1.213099024,"remaining_time":0.06519288747},
{"learn":[3.031624378],"iteration":949,"passed_time":1.214051086,"remaining_time":0.0638974256},
{"learn":[3.031579019],"iteration":950,"passed_time":1.214860319,"remaining_time":0.06259532663},
{"learn":[3.031465808],"iteration":951,"passed_time":1.215860372,"remaining_time":0.06130388429},
{"learn":[3.029332943],"iteration":952,"passed_time":1.217143933,"remaining_time":0.0600270355},
{"learn":[3.027394367],"iteration":953,"passed_time":1.218331033,"remaining_time":0.0587455215},
{"learn":[3.026284336],"iteration":954,"passed_time":1.219315186,"remaining_time":0.05745464229},
{"learn":[3.024658341],"iteration":955,"passed_time":1.220239163,"remaining_time":0.05616163512},
{"learn":[3.021521315],"iteration":956,"passed_time":1.221161793,"remaining_time":0.05486933864},
{"learn":[3.021139308],"iteration":957,"passed_time":1.222011621,"remaining_time":0.05357462223},
{"learn":[3.021095467],"iteration":958,"passed_time":1.222757758,"remaining_time":0.05227640048},
{"learn":[3.019985581],"iteration":959,"passed_time":1.223768356,"remaining_time":0.05099034818},
{"learn":[3.019941317],"iteration":960,"passed_time":1.224819157,"remaining_time":0.04970650065},
{"learn":[3.018336886],"iteration":961,"passed_time":1.225896511,"remaining_time":0.0484241865},
{"learn":[3.016620741],"iteration":962,"passed_time":1.226838283,"remaining_time":0.04713708876},
{"learn":[3.01572343],"iteration":963,"passed_time":1.227808204,"remaining_time":0.04585175867},
{"learn":[3.015348922],"iteration":964,"passed_time":1.22876072,"remaining_time":0.04456645097},
{"learn":[3.014777596],"iteration":965,"passed_time":1.229680057,"remaining_time":0.04328066455},
{"learn":[3.0119558],"iteration":966,"passed_time":1.230565235,"remaining_time":0.04199447026},
{"learn":[3.009558784],"iteration":967,"passed_time":1.231489216,"remaining_time":0.0407103873},
{"learn":[3.009020986],"iteration":968,"passed_time":1.23252384,"remaining_time":0.03943058726},
{"learn":[3.008174594],"iteration":969,"passed_time":1.23344561,"remaining_time":0.03814780239},
{"learn":[3.005067751],"iteration":970,"passed_time":1.234337833,"remaining_time":0.03686487864},
{"learn":[3.002971349],"iteration":971,"passed_time":1.235261804,"remaining_time":0.03558367337},
{"learn":[3.001871283],"iteration":972,"passed_time":1.236166436,"remaining_time":0.03430266575},
{"learn":[3.000190086],"iteration":973,"passed_time":1.237123389,"remaining_time":0.03302382764},
{"learn":[2.999028654],"iteration":974,"passed_time":1.23802291,"remaining_time":0.03174417718},
{"learn":[2.996566113],"iteration":975,"passed_time":1.239040914,"remaining_time":0.03046821921},
{"learn":[2.993990125],"iteration":976,"passed_time":1.239931028,"remaining_time":0.02918977855},
{"learn":[2.991868367],"iteration":977,"passed_time":1.240809468,"remaining_time":0.02791186942},
{"learn":[2.9897001],"iteration":978,"passed_time":1.241668214,"remaining_time":0.02663435393},
{"learn":[2.986960259],"iteration":979,"passed_time":1.242596471,"remaining_time":0.02535911166},
{"learn":[2.985841682],"iteration":980,"passed_time":1.243433156,"remaining_time":0.02408280323},
{"learn":[2.98438727],"iteration":981,"passed_time":1.244327888,"remaining_time":0.02280845417},
{"learn":[2.984116804],"iteration":982,"passed_time":1.245228979,"remaining_time":0.02153498742},
{"learn":[2.982905431],"iteration":983,"passed_time":1.24619262,"remaining_time":0.02026329463},
{"learn":[2.982384945],"iteration":984,"passed_time":1.247108507,"remaining_time":0.0189915001},
{"learn":[2.981527059],"iteration":985,"passed_time":1.248010738,"remaining_time":0.0177202336},
{"learn":[2.979135847],"iteration":986,"passed_time":1.248980523,"remaining_time":0.01645060465},
{"learn":[2.979061331],"iteration":987,"passed_time":1.249880544,"remaining_time":0.01518073536},
{"learn":[2.976716671],"iteration":988,"passed_time":1.250765096,"remaining_time":0.01391144192},
{"learn":[2.975425388],"iteration":989,"passed_time":1.251678135,"remaining_time":0.01264321349},
{"learn":[2.975364198],"iteration":990,"passed_time":1.252656786,"remaining_time":0.01137629776},
{"learn":[2.97474337],"iteration":991,"passed_time":1.254147005,"remaining_time":0.01011408875},
{"learn":[2.972981045],"iteration":992,"passed_time":1.255031456,"remaining_time":0.008847150246},
{"learn":[2.970175177],"iteration":993,"passed_time":1.255982226,"remaining_time":0.007581381644},
{"learn":[2.968510377],"iteration":994,"passed_time":1.256873066,"remaining_time":0.006315945055},
{"learn":[2.967237645],"iteration":995,"passed_time":1.257879882,"remaining_time":0.005051726433},
{"learn":[2.966767948],"iteration":996,"passed_time":1.258891365,"remaining_time":0.003788038208},
{"learn":[2.965074901],"iteration":997,"passed_time":1.259836741,"remaining_time":0.002524722928},
{"learn":[2.962386252],"iteration":998,"passed_time":1.260881512,"remaining_time":0.001262143656},
{"learn":[2.960295879],"iteration":999,"passed_time":1.261793001,"remaining_time":0}
]}